Workbook

Sheet 2026底表
A1: 生产指标 | B1: 统计时间 | C1: 46296 | D1: 46297 | E1: 46298 | F1: 46299 | G1: 46300 | H1: 46301 | I1: 46302 | J1: 46303 | K1: 46304 | L1: 46305 | M1: 46306 | N1: 46307 | O1: 46308 | P1: 46309 | Q1: 46310 | R1: 46311 | S1: 46312 | T1: 46313 | U1: 46314 | V1: 46315 | W1: 46316 | X1: 46317 | Y1: 46318 | Z1: 46319 | AA1: 46320 | AB1: 46321 | AC1: 46322 | AD1: 46323 | AE1: 46324 | AF1: 46325 | AG1: 46326 | AW1: 生产指标 | AX1: 统计时间 | AY1: 46321
A2: 天气 | B2: 2025 当日最低温度 | AW2: 天气 | AX2: 2025 当日最低温度
B3: 2025 当日最高温度 | AX3: 2025 当日最高温度
B4: 2025 气象 | AX4: 2025 气象
B5: 2026 当日最低温度 | AX5: 2026 当日最低温度
B6: 2026 当日最高温度 | AX6: 2026 当日最高温度
B7: 2026 气象 | AX7: 2026 气象
A8: 汇总 | AW8: 汇总
A9: 运行方式 炉/机 | AW9: 运行方式 炉/机
B11: 计划 | AX11: 计划
A12: 发电量 （万千万时) | AW12: 发电量 （万千万时)
B14: 计划值 | AX14: 计划值
B15: 与计划差值 | AX15: 与计划差值
B16: 同比差值 | AX16: 同比差值
A17: 上网供电量 （万千万时) | AW17: 上网供电量 （万千万时)
B19: 计划值 | AX19: 计划值
B20: 与计划差值 | AX20: 与计划差值
B21: 同比差值 | AX21: 同比差值
A22: 综合厂 用电量 （万千万时) | AW22: 综合厂 用电量 （万千万时)
B24: 计划值 | AX24: 计划值
B25: 与计划差值 | AX25: 与计划差值
B26: 同比差值 | AX26: 同比差值
A27: 综合 厂用电率 （%） | AW27: 综合 厂用电率 （%）
B29: 计划值 | AX29: 计划值
B30: 与计划差值 | AX30: 与计划差值
B31: 同比差值 | AX31: 同比差值
A32: 外供汽量 (吨） | AW32: 外供汽量 (吨）
B34: 计划值 | AX34: 计划值
B35: 与计划差值 | AX35: 与计划差值
B36: 同比差值 | AX36: 同比差值
A37: 供首站汽量 （吨） | AW37: 供首站汽量 （吨）
B41: 同比差值 | AX41: 同比差值
A42: 天然气炉 供汽量 （吨） | AW42: 天然气炉 供汽量 （吨）
B44: 同比差值 | AX44: 同比差值
A45: 外供热总量 （吉焦） | AW45: 外供热总量 （吉焦）
B47: 计划值 | AX47: 计划值
B48: 与计划差值 | AX48: 与计划差值
B49: 同比差值 | AX49: 同比差值
A50: 电厂耗原煤量 （吨） | AW50: 电厂耗原煤量 （吨）
B52: 计划值 | AX52: 计划值
B53: 与计划差值 | AX53: 与计划差值
B54: 同比差值 | AX54: 同比差值
A55: 水炉耗原煤量 （吨） | AW55: 水炉耗原煤量 （吨）
B57: 计划值 | AX57: 计划值
B58: 与计划差值 | AX58: 与计划差值
B59: 同比差值 | AX59: 同比差值
A60: 电厂耗标煤量 （吨） | AW60: 电厂耗标煤量 （吨）
B62: 计划值 | AX62: 计划值
B63: 与计划差值 | AX63: 与计划差值
B64: 同比差值 | AX64: 同比差值
A65: 水炉耗标煤量 （吨） | AW65: 水炉耗标煤量 （吨）
B67: 计划值 | AX67: 计划值
B68: 与计划差值 | AX68: 与计划差值
B69: 同比差值 | AX69: 同比差值
A70: 耗天然气量 （立方米） | AW70: 耗天然气量 （立方米）
B72: 计划值 | AX72: 计划值
B73: 与计划差值 | AX73: 与计划差值
B74: 同比差值 | AX74: 同比差值
A75: 总自来水量 （吨） | AW75: 总自来水量 （吨）
B77: 同比差值 | AX77: 同比差值
A78: 再生水量 （吨） | AW78: 再生水量 （吨）
B80: 同比差值 | AX80: 同比差值
A81: 电厂耗水量 （吨） | AW81: 电厂耗水量 （吨）
B83: 计划值 | AX83: 计划值
B84: 与计划差值 | AX84: 与计划差值
B85: 同比差值 | AX85: 同比差值
A86: 耗柴油量 （吨） | AW86: 耗柴油量 （吨）
B88: 计划值 | AX88: 计划值
B89: 与计划差值 | AX89: 与计划差值
B90: 同比差值 | AX90: 同比差值
A91: 外购电量 （千万时） | AW91: 外购电量 （千万时）
B93: 计划值 | AX93: 计划值
B94: 与计划差值 | AX94: 与计划差值
B95: 同比差值 | AX95: 同比差值
A96: 石灰石 (含水炉）（吨） | AW96: 石灰石 (含水炉）（吨）
B98: 计划值 | AX98: 计划值
B99: 与计划差值 | AX99: 与计划差值
B100: 同比差值 | AX100: 同比差值
A101: 氨水 (含水炉） （吨） | AW101: 氨水 (含水炉） （吨）
B103: 计划值 | AX103: 计划值
B104: 与计划差值 | AX104: 与计划差值
B105: 同比差值 | AX105: 同比差值
A106: 耗酸量 （吨） | AW106: 耗酸量 （吨）
B108: 计划值 | AX108: 计划值
B109: 与计划差值 | AX109: 与计划差值
B110: 同比差值 | AX110: 同比差值
A111: 耗碱量 （吨） | AW111: 耗碱量 （吨）
B113: 计划值 | AX113: 计划值
B114: 与计划差值 | AX114: 与计划差值
B115: 同比差值 | AX115: 同比差值
A116: 钢球 （吨） | AW116: 钢球 （吨）
B118: 同比差值 | AX118: 同比差值
A119: 脱硫耗水量 (含水炉） （吨） | AW119: 脱硫耗水量 (含水炉） （吨）
B121: 同比差值 | AX121: 同比差值
A122: 脱硫耗电量 (含水炉） （千瓦时） | AW122: 脱硫耗电量 (含水炉） （千瓦时）
B124: 同比差值 | AX124: 同比差值
A125: 高减汽量 （吨） | AW125: 高减汽量 （吨）
A127: 粉煤灰量 （吨） | AW127: 粉煤灰量 （吨）
B129: 同比差值 | AX129: 同比差值
A130: 粉煤灰成本 （元） | AW130: 粉煤灰成本 （元）
...

Sheet 2026.10
A1: 生产指标 | B1: 统计时间 | C1: 46296 | D1: 46297 | E1: 46298 | F1: 46299 | G1: 46300 | H1: 46301 | I1: 46302 | J1: 46303 | K1: 46304 | L1: 46305 | M1: 46306 | N1: 46307 | O1: 46308 | P1: 46309 | Q1: 46310 | R1: 46311 | S1: 46312 | T1: 46313 | U1: 46314 | V1: 46315 | W1: 46316 | X1: 46317 | Y1: 46318 | Z1: 46319 | AA1: 46320 | AB1: 46321 | AC1: 46322 | AD1: 46323 | AE1: 46324 | AF1: 46325 | AG1: 46326 | AI1: 46322 | AJ1: AC | AU1: =U129 -> 0
A2: 天气 | B2: 2025 当日最低温度 | C2: 19 | D2: 20 | E2: 20 | F2: 19 | G2: 17 | H2: 14 | I2: 14 | J2: 3 | K2: 11 | L2: 12 | M2: 14 | N2: 14 | O2: 16 | P2: 15 | Q2: 14 | R2: 12 | S2: 10 | T2: 5 | U2: 4 | V2: 4 | W2: 6 | X2: 6 | Y2: 5 | Z2: 6 | AA2: 9 | AB2: 6 | AC2: 6 | AD2: 9 | AE2: 14 | AF2: 9 | AG2: 9
B3: 2025 当日最高温度 | C3: 30 | D3: 25 | E3: 27 | F3: 27 | G3: 25 | H3: 23 | I3: 24 | J3: 20 | K3: 14 | L3: 16 | M3: 19 | N3: 21 | O3: 21 | P3: 23 | Q3: 20 | R3: 15 | S3: 19 | T3: 11 | U3: 10 | V3: 10 | W3: 10 | X3: 12 | Y3: 15 | Z3: 12 | AA3: 16 | AB3: 14 | AC3: 10 | AD3: 16 | AE3: 18 | AF3: 15 | AG3: 15
B4: 2025 气象 | C4: 晴 西北风4级 | D4: 晴 西北风3级 | E4: 晴 南风3级 | F4: 晴 西南风3级 | G4: 多云 西南风3级 | H4: 阴~多云 西北风3级 | I4: 晴 北风5级 | J4: 晴 北风3级 | K4: 阴 西南风2级 | L4: 晴 北风4级 | M4: 阴-晴 西南风3级 | N4: 晴 西南风2级 | O4: 阴-多云 东南风3级 | P4: 小雨-多云 南风3级 | Q4: 多云-小雨 南风3级 | R4: 多云 北风5级 | S4: 阴 北风6级 | T4: 晴转多云 东北风4级 | U4: 晴 北风4级 | V4: 晴 北风4级 | W4: 晴 北风5级 | X4: 晴 北风4级 | Y4: 晴 北风5级 | Z4: 阴 北风3级 | AA4: 阴转小雨 西风3级 | AB4: 多云转晴 西北风4级 | AC4: 晴 北风3级 | AD4: 多云转阴 南风4级 | AE4: 多云转小雨 西南风5级 | AF4: 阵雨转小雨 东北风4级 | AG4: 多云 西北风4级
B5: 2026 当日最低温度 | C5: 14 | D5: 14 | E5: 17 | F5: 14 | G5: 14 | H5: 14 | I5: 15 | J5: 15 | K5: 18 | L5: 18 | M5: 15 | N5: 14 | O5: 14 | P5: 13 | Q5: 14 | R5: 16 | S5: 15 | T5: 13 | U5: 13 | V5: 10 | W5: 9 | X5: 9 | Y5: 12 | Z5: 10 | AA5: 10 | AB5: 10 | AC5: 8 | AD5: 8
B6: 2026 当日最高温度 | C6: 20 | D6: 22 | E6: 21 | F6: 19 | G6: 19 | H6: 19 | I6: 23 | J6: 25 | K6: 24 | L6: 24 | M6: 23 | N6: 23 | O6: 20 | P6: 22 | Q6: 24 | R6: 21 | S6: 23 | T6: 21 | U6: 20 | V6: 19 | W6: 12 | X6: 16 | Y6: 17 | Z6: 18 | AA6: 18 | AB6: 15 | AC6: 13 | AD6: 17
B7: 2026 气象 | C7: 晴 西北风3级 | D7: 晴 南风1级 | E7: 多云转雷阵雨 南风2级 | F7: 阴转多云 西北风3级 | G7: 晴 北风4级 | H7: 晴 西北风3级 | I7: 晴 西风3级 | J7: 晴 西南风4级 | K7: 晴 南风5级 | L7: 阴 南风1级 | M7: 多云 南风1级 | N7: 雾 南风3级 | O7: 晴 西风1级 | P7: 多云转小雨 南风2级 | Q7: 雾霾转阴 西北风1级 | R7: 多云 东南风3级 | S7: 阴小雨转大雨 南风5级 | T7: 阴转多云 东北风2级 | U7: 阴 东风1级 | V7: 小雨转晴 西北风5级 | W7: 晴 北风5级 | X7: 多云 南风3级 | Y7: 阴转晴 南风3级 | Z7: 阴转晴 东北风3级 | AA7: 晴 北风3级 | AB7: 多云转晴 北风4级 | AC7: 晴 北风6级 | AD7: 多云 南风2级
A8: 汇总
A9: 运行方式 炉/机 | P9: 46310 | Q9: 轻度雾霾转阴 | R9: 24℃ | S9: 14℃ | T9: 西北风1级 | AU9: =AO155 -> 0
P10: 46311 | Q10: 多云 | R10: 21℃ | S10: 16℃ | T10: 东南风3级 | AU10: =U147 -> 0.952076
B11: 计划 | P11: 46312 | Q11: 阴偶有小雨转大雨 | R11: 23℃ | S11: 15℃ | T11: 南风5级 | AU11: =AO147 -> 0
A12: 发电量 （万千万时) | C12: =C173 -> 0 | D12: =D173 -> 0 | E12: =E173 -> 0 | F12: =F173 -> 0 | G12: =G173 -> 0 | H12: =H173 -> 0 | I12: =I173 -> 0 | J12: =J173 -> 0 | ... O12: =O173 -> 0 | P12: 46313 | Q12: 阴转多云 | R12: 21℃ | S12: 13℃ | T12: 东北风2级 | U12: =U173 -> 0 | V12: =V173 -> 0 | W12: =W173 -> 0 | X12: =X173 -> 0 | Y12: =Y173 -> 0 | Z12: =Z173 -> 0 | AA12: =AA173 -> 0 | AB12: =AB173 -> 0 | ... AG12: =AG173 -> 0 | AH12: =SUM(C12:AG12) -> 46313 | AU12: =U186 -> 1.74
C13: =C174 -> 0 | D13: =D174 -> 0 | E13: =E174 -> 0 | F13: =F174 -> 0 | G13: =G174 -> 0 | H13: =H174 -> 0 | I13: =I174 -> 0 | J13: =J174 -> 0 | ... O13: =O174 -> 0 | P13: 46314 | Q13: 阴 | R13: 20℃ | S13: 13℃ | T13: 东风1级 | U13: =U174 -> 0 | V13: =V174 -> 0 | W13: =W174 -> 0 | X13: =X174 -> 0 | Y13: =Y174 -> 0 | Z13: =Z174 -> 0 | AA13: =AA174 -> 0 | AB13: =AB174 -> 0 | ... AG13: =AG174 -> 0 | AH13: =SUM(C13:AG13) -> 46314 | AU13: =AO188 -> 0
B14: 计划值 | C14: =C175 -> 0 | D14: =D175 -> 0 | E14: =E175 -> 0 | F14: =F175 -> 0 | G14: =G175 -> 0 | H14: =H175 -> 0 | I14: =I175 -> 0 | J14: =J175 -> 0 | ... AG14: =AG175 -> 0 | AH14: =SUM(C14:AG14) -> 0 | AU14: =U181 -> 0
B15: 与计划差值 | C15: =C176 -> 0 | D15: =D176 -> 0 | E15: =E176 -> 0 | F15: =F176 -> 0 | G15: =G176 -> 0 | H15: =H176 -> 0 | I15: =I176 -> 0 | J15: =J176 -> 0 | ... AG15: =AG176 -> 0 | AH15: =SUM(C15:AG15) -> 0 | AU15: =AO181 -> 0
B16: 同比差值 | C16: =C177 -> 0 | D16: =D177 -> 0 | E16: =E177 -> 0 | F16: =F177 -> 0 | G16: =G177 -> 0 | H16: =H177 -> 0 | I16: =I177 -> 0 | J16: =J177 -> 0 | ... AG16: =AG177 -> 0 | AH16: =SUM(C16:AG16) -> 0 | AU16: =U189 -> #DIV/0!
A17: 上网供电量 （万千万时) | C17: =C178 -> 0 | D17: =D178 -> 0 | E17: =E178 -> 0 | F17: =F178 -> 0 | G17: =G178 -> 0 | H17: =H178 -> 0 | I17: =I178 -> 0 | J17: =J178 -> 0 | ... AG17: =AG178 -> 0 | AH17: =SUM(C17:AG17) -> 0 | AU17: =AO191 -> 0
C18: =C179 -> 0 | D18: =D179 -> 0 | E18: =E179 -> 0 | F18: =F179 -> 0 | G18: =G179 -> 0 | H18: =H179 -> 0 | I18: =I179 -> 0 | J18: =J179 -> 0 | ... AG18: =AG179 -> 0 | AH18: =SUM(C18:AG18) -> 0 | AU18: =U192 -> #DIV/0!
B19: 计划值 | C19: =C180 -> 0 | D19: =D180 -> 0 | E19: =E180 -> 0 | F19: =F180 -> 0 | G19: =G180 -> 0 | H19: =H180 -> 0 | I19: =I180 -> 0 | J19: =J180 -> 0 | ... AG19: =AG180 -> 0 | AH19: =SUM(C19:AG19) -> 0 | AU19: =AO194 -> 1069
B20: 与计划差值 | C20: =C181 -> 0 | D20: =D181 -> 0 | E20: =E181 -> 0 | F20: =F181 -> 0 | G20: =G181 -> 0 | H20: =H181 -> 0 | I20: =I181 -> 0 | J20: =J181 -> 0 | ... AG20: =AG181 -> 0 | AH20: =SUM(C20:AG20) -> 0 | AU20: =AU2/((AU4-AU21)*U137/1000) -> #DIV/0!
B21: 同比差值 | C21: =C182 -> 0 | D21: =D182 -> 0 | E21: =E182 -> 0 | F21: =F182 -> 0 | G21: =G182 -> 0 | H21: =H182 -> 0 | I21: =I182 -> 0 | J21: =J182 -> 0 | ... AG21: =AG182 -> 0 | AH21: =SUM(C21:AG21) -> 0 | AU21: =U300 -> 0
A22: 综合厂 用电量 （万千万时) | C22: =C183 -> 0.48 | D22: =D183 -> 0.54 | E22: =E183 -> 0.54 | F22: =F183 -> 0.6 | G22: =G183 -> 0.54 | H22: =H183 -> 0.6 | I22: =I183 -> 0.54 | J22: =J183 -> 0.72 | ... AG22: =AG183 -> 6.19975 | AH22: =SUM(C22:AG22) -> 84.709338
C23: =C184 -> 0.54 | D23: =D184 -> 0.54 | E23: =E184 -> 0.54 | F23: =F184 -> 0.54 | G23: =G184 -> 0.54 | H23: =H184 -> 0.54 | I23: =I184 -> 0.48 | J23: =J184 -> 0.72 | ... AG23: =AG184 -> 0 | AH23: =SUM(C23:AG23) -> 54.96
B24: 计划值 | C24: =C185 -> 0 | D24: =D185 -> 0 | E24: =E185 -> 0 | F24: =F185 -> 0 | G24: =G185 -> 0 | H24: =H185 -> 0 | I24: =I185 -> 0 | J24: =J185 -> 0 | ... AG24: =AG185 -> 0 | AH24: =SUM(C24:AG24) -> 0
B25: 与计划差值 | C25: =C186 -> 0.54 | D25: =D186 -> 0.54 | E25: =E186 -> 0.54 | F25: =F186 -> 0.54 | G25: =G186 -> 0.54 | H25: =H186 -> 0.54 | I25: =I186 -> 0.48 | J25: =J186 -> 0.72 | ... AG25: =AG186 -> 0 | AH25: =SUM(C25:AG25) -> 54.96
B26: 同比差值 | C26: =C187 -> 0.06 | D26: =D187 -> 0 | E26: =E187 -> 0 | F26: =F187 -> -0.06 | G26: =G187 -> 0 | H26: =H187 -> -0.06 | I26: =I187 -> -0.06 | J26: =J187 -> 0 | ... AG26: =AG187 -> -6.19975 | AH26: =SUM(C26:AG26) -> -29.749338
A27: 综合 厂用电率 （%） | C27: =C188 -> #DIV/0! | D27: =D188 -> #DIV/0! | E27: =E188 -> #DIV/0! | F27: =F188 -> #DIV/0! | G27: =G188 -> #DIV/0! | H27: =H188 -> #DIV/0! | I27: =I188 -> #DIV/0! | J27: =J188 -> #DIV/0! | ... AF27: =AF188 -> #DIV/0! | AH27: =AH22/AH12 -> 0.0018290618
C28: =C189 -> #DIV/0! | D28: =D189 -> #DIV/0! | E28: =E189 -> #DIV/0! | F28: =F189 -> #DIV/0! | G28: =G189 -> #DIV/0! | H28: =H189 -> #DIV/0! | I28: =I189 -> #DIV/0! | J28: =J189 -> #DIV/0! | ... AG28: =AG189 -> #DIV/0! | AH28: =AH23/AH13 -> 0.0011866822
B29: 计划值 | C29: =C190 -> 0 | D29: =D190 -> 0 | E29: =E190 -> 0 | F29: =F190 -> 0 | G29: =G190 -> 0 | H29: =H190 -> 0 | I29: =I190 -> 0 | J29: =J190 -> 0 | ... AH29: =AH190 -> 0
B30: 与计划差值 | C30: =C191 -> #DIV/0! | D30: =D191 -> #DIV/0! | E30: =E191 -> #DIV/0! | F30: =F191 -> #DIV/0! | G30: =G191 -> #DIV/0! | H30: =H191 -> #DIV/0! | I30: =I191 -> #DIV/0! | J30: =J191 -> #DIV/0! | ... AG30: =AG191 -> #DIV/0! | AH30: =SUM(C30:AG30) -> #DIV/0!
B31: 同比差值 | C31: =C192 -> #DIV/0! | D31: =D192 -> #DIV/0! | E31: =E192 -> #DIV/0! | F31: =F192 -> #DIV/0! | G31: =G192 -> #DIV/0! | H31: =H192 -> #DIV/0! | I31: =I192 -> #DIV/0! | J31: =J192 -> #DIV/0! | ... AG31: =AG192 -> #DIV/0! | AH31: =SUM(C31:AG31) -> #DIV/0!
A32: 外供汽量 (吨） | C32: =C193+C432 -> 0 | D32: =D193+D432 -> 0 | E32: =E193+E432 -> 0 | F32: =F193+F432 -> 0 | G32: =G193+G432 -> 0 | H32: =H193+H432 -> 0 | I32: =I193+I432 -> 0 | J32: =J193+J432 -> 0 | ... AG32: =AG193+AG432 -> 0 | AH32: =SUM(C32:AG32) -> 0
C33: =C194 -> 0 | D33: =D194 -> 0 | E33: =E194 -> 0 | F33: =F194 -> 0 | G33: =G194 -> 0 | H33: =H194 -> 0 | I33: =I194 -> 0 | J33: =J194 -> 0 | ... AG33: =AG194 -> 0 | AH33: =SUM(C33:AG33) -> 0
B34: 计划值 | C34: =C195 -> 0 | D34: =D195 -> 0 | E34: =E195 -> 0 | F34: =F195 -> 0 | G34: =G195 -> 0 | H34: =H195 -> 0 | I34: =I195 -> 0 | J34: =J195 -> 0 | ... AG34: =AG195 -> 0 | AH34: =SUM(C34:AG34) -> 0
B35: 与计划差值 | C35: =C33-C34 -> 0 | D35: =D33-D34 -> 0 | E35: =E33-E34 -> 0 | F35: =F33-F34 -> 0 | G35: =G33-G34 -> 0 | H35: =H33-H34 -> 0 | I35: =I33-I34 -> 0 | J35: =J33-J34 -> 0 | ... AG35: =AG33-AG34 -> 0 | AH35: =SUM(C35:AG35) -> 0
B36: 同比差值 | C36: =C33-C32 -> 0 | D36: =D33-D32 -> 0 | E36: =E33-E32 -> 0 | F36: =F33-F32 -> 0 | G36: =G33-G32 -> 0 | H36: =H33-H32 -> 0 | I36: =I33-I32 -> 0 | J36: =J33-J32 -> 0 | ... AG36: =AG33-AG32 -> 0 | AH36: =SUM(C36:AG36) -> 0
A37: 供首站汽量 （吨） | C37: =C459+C475 -> 0 | D37: =D459+D475 -> 0 | E37: =E459+E475 -> 0 | F37: =F459+F475 -> 0 | G37: =G459+G475 -> 0 | H37: =H459+H475 -> 0 | I37: =I459+I475 -> 0 | J37: =J459+J475 -> 0 | ... AG37: =AG459+AG475 -> 0 | AH37: =SUM(C37:AG37) -> 0
C40: =C460+C476 -> 0 | D40: =D460+D476 -> 0 | E40: =E460+E476 -> 0 | F40: =F460+F476 -> 0 | G40: =G460+G476 -> 0 | H40: =H460+H476 -> 0 | I40: =I460+I476 -> 0 | J40: =J460+J476 -> 0 | ... AG40: =AG460+AG476 -> 0 | AH40: =SUM(C40:AG40) -> 0
B41: 同比差值 | C41: =C40-C37 -> 0 | D41: =D40-D37 -> 0 | E41: =E40-E37 -> 0 | F41: =F40-F37 -> 0 | G41: =G40-G37 -> 0 | H41: =H40-H37 -> 0 | I41: =I40-I37 -> 0 | J41: =J40-J37 -> 0 | ... AG41: =AG40-AG37 -> 0 | AH41: =SUM(C41:AG41) -> 0
A42: 天然气炉 供汽量 （吨） | C42: =C432 -> 0 | D42: =D432 -> 0 | E42: =E432 -> 0 | F42: =F432 -> 0 | G42: =G432 -> 0 | H42: =H432 -> 0 | I42: =I432 -> 0 | J42: =J432 -> 0 | ... AG42: =AG432 -> 0 | AH42: =SUM(C42:AG42) -> 0
C43: =C433 -> 0 | D43: =D433 -> 0 | E43: =E433 -> 0 | F43: =F433 -> 0 | G43: =G433 -> 0 | H43: =H433 -> 0 | I43: =I433 -> 0 | J43: =J433 -> 0 | ... AG43: =AG433 -> 0 | AH43: =SUM(C43:AG43) -> 0
B44: 同比差值 | C44: =C43-C42 -> 0 | D44: =D43-D42 -> 0 | E44: =E43-E42 -> 0 | F44: =F43-F42 -> 0 | G44: =G43-G42 -> 0 | H44: =H43-H42 -> 0 | I44: =I43-I42 -> 0 | J44: =J43-J42 -> 0 | ... AG44: =AG43-AG42 -> 0 | AH44: =SUM(C44:AG44) -> 0
A45: 外供热总量 （吉焦） | C45: =C33*2.951694+C500+C501+C498 -> 0 | AH45: =SUM(C45:AG45) -> 0
C46: =C33*2.951694+C346+C469+C498+C485 -> 0 | D46: =D33*2.951694+D346+D469+D498+D485 -> 0 | E46: =E33*2.951694+E346+E469+E498+E485 -> 0 | F46: =F33*2.951694+F346+F469+F498+F485 -> 0 | G46: =G33*2.951694+G346+G469+G498+G485 -> 0 | H46: =H33*2.951694+H346+H469+H498+H485 -> 0 | I46: =I33*2.951694+I346+I469+I498+I485 -> 0 | J46: =J33*2.951694+J346+J469+J498+J485 -> 0 | ... AG46: =AG33*2.951694+AG346+AG469+AG498+AG485 -> 0 | AH46: =SUM(C46:AG46) -> 15210
B47: 计划值 | C47: =C200+C347+C436 -> 0 | D47: =D200+D347+D436 -> 0 | E47: =E200+E347+E436 -> 0 | F47: =F200+F347+F436 -> 0 | G47: =G200+G347+G436 -> 0 | H47: =H200+H347+H436 -> 0 | I47: =I200+I347+I436 -> 0 | J47: =J200+J347+J436 -> 0 | ... AG47: =AG200+AG347+AG436 -> 5000 | AH47: =SUM(C47:AG47) -> 34200
B48: 与计划差值 | C48: =C46-C47 -> 0 | D48: =D46-D47 -> 0 | E48: =E46-E47 -> 0 | F48: =F46-F47 -> 0 | G48: =G46-G47 -> 0 | H48: =H46-H47 -> 0 | I48: =I46-I47 -> 0 | J48: =J46-J47 -> 0 | ... AG48: =AG46-AG47 -> -5000 | AH48: =SUM(C48:AG48) -> -18990
B49: 同比差值 | C49: =C46-C45 -> 0 | D49: =D46-D45 -> 0 | E49: =E46-E45 -> 0 | F49: =F46-F45 -> 0 | G49: =G46-G45 -> 0 | H49: =H46-H45 -> 0 | I49: =I46-I45 -> 0 | J49: =J46-J45 -> 0 | ... AG49: =AG46-AG45 -> 0 | AH49: =SUM(C49:AG49) -> 15210
A50: 电厂耗原煤量 （吨） | C50: =C203 -> 0 | D50: =D203 -> 0 | E50: =E203 -> 0 | F50: =F203 -> 0 | G50: =G203 -> 0 | H50: =H203 -> 0 | I50: =I203 -> 0 | J50: =J203 -> 0 | ... AG50: =AG203 -> 236 | AH50: =SUM(C50:AG50) -> 236
C51: =C204 -> 0 | D51: =D204 -> 0 | E51: =E204 -> 0 | F51: =F204 -> 0 | G51: =G204 -> 0 | H51: =H204 -> 0 | I51: =I204 -> 0 | J51: =J204 -> 0 | ... AG51: =AG204 -> 0 | AH51: =SUM(C51:AG51) -> 0
B52: 计划值 | C52: =C205 -> 0 | D52: =D205 -> 0 | E52: =E205 -> 0 | F52: =F205 -> 0 | G52: =G205 -> 0 | H52: =H205 -> 0 | I52: =I205 -> 0 | J52: =J205 -> 0 | ... AG52: =AG205 -> 0 | AH52: =SUM(C52:AG52) -> 0
B53: 与计划差值 | C53: =C206 -> 0 | D53: =D206 -> 0 | E53: =E206 -> 0 | F53: =F206 -> 0 | G53: =G206 -> 0 | H53: =H206 -> 0 | I53: =I206 -> 0 | J53: =J206 -> 0 | ... AG53: =AG206 -> 0 | AH53: =SUM(C53:AG53) -> 0
B54: 同比差值 | C54: =C207 -> 0 | D54: =D207 -> 0 | E54: =E207 -> 0 | F54: =F207 -> 0 | G54: =G207 -> 0 | H54: =H207 -> 0 | I54: =I207 -> 0 | J54: =J207 -> 0 | ... AG54: =AG207 -> -236 | AH54: =SUM(C54:AG54) -> -236
A55: 水炉耗原煤量 （吨） | C55: =C350 -> 0 | D55: =D350 -> 0 | E55: =E350 -> 0 | F55: =F350 -> 0 | G55: =G350 -> 0 | H55: =H350 -> 0 | I55: =I350 -> 0 | J55: =J350 -> 0 | ... AG55: =AG350 -> 322 | AH55: =SUM(C55:AG55) -> 1867
C56: =C351 -> 0 | D56: =D351 -> 0 | E56: =E351 -> 0 | F56: =F351 -> 0 | G56: =G351 -> 0 | H56: =H351 -> 0 | I56: =I351 -> 0 | J56: =J351 -> 0 | ... AG56: =AG351 -> 0 | AH56: =SUM(C56:AG56) -> 739
B57: 计划值 | C57: =C352 -> 0 | D57: =D352 -> 0 | E57: =E352 -> 0 | F57: =F352 -> 0 | G57: =G352 -> 0 | H57: =H352 -> 0 | I57: =I352 -> 0 | J57: =J352 -> 0 | ... AG57: =AG352 -> 286.95231 | AH57: =SUM(C57:AG57) -> 1962.7538
B58: 与计划差值 | C58: =C353 -> 0 | D58: =D353 -> 0 | E58: =E353 -> 0 | F58: =F353 -> 0 | G58: =G353 -> 0 | H58: =H353 -> 0 | I58: =I353 -> 0 | J58: =J353 -> 0 | ... AG58: =AG353 -> -286.95231 | AH58: =SUM(C58:AG58) -> -1223.7538
B59: 同比差值 | C59: =C354 -> 0 | D59: =D354 -> 0 | E59: =E354 -> 0 | F59: =F354 -> 0 | G59: =G354 -> 0 | H59: =H354 -> 0 | I59: =I354 -> 0 | J59: =J354 -> 0 | ... AG59: =AG354 -> -322 | AH59: =SUM(C59:AG59) -> -1128
A60: 电厂耗标煤量 （吨） | C60: =C208 -> 0 | D60: =D208 -> 0 | E60: =E208 -> 0 | F60: =F208 -> 0 | G60: =G208 -> 0 | H60: =H208 -> 0 | I60: =I208 -> 0 | J60: =J208 -> 0 | ... AG60: =AG208 -> 0 | AH60: =SUM(C60:AG60) -> 0
C61: =C209 -> 0 | D61: =D209 -> 0 | E61: =E209 -> 0 | F61: =F209 -> 0 | G61: =G209 -> 0 | H61: =H209 -> 0 | I61: =I209 -> 0 | J61: =J209 -> 0 | ... AG61: =AG209 -> 0 | AH61: =SUM(C61:AG61) -> 0
B62: 计划值 | C62: =C210 -> 0 | D62: =D210 -> 0 | E62: =E210 -> 0 | F62: =F210 -> 0 | G62: =G210 -> 0 | H62: =H210 -> 0 | I62: =I210 -> 0 | J62: =J210 -> 0 | ... AG62: =AG210 -> 0 | AH62: =SUM(C62:AG62) -> 0
B63: 与计划差值 | C63: =C211 -> 0 | D63: =D211 -> 0 | E63: =E211 -> 0 | F63: =F211 -> 0 | G63: =G211 -> 0 | H63: =H211 -> 0 | I63: =I211 -> 0 | J63: =J211 -> 0 | ... AG63: =AG211 -> 0 | AH63: =SUM(C63:AG63) -> 0
B64: 同比差值 | C64: =C212 -> 0 | D64: =D212 -> 0 | E64: =E212 -> 0 | F64: =F212 -> 0 | G64: =G212 -> 0 | H64: =H212 -> 0 | I64: =I212 -> 0 | J64: =J212 -> 0 | ... AG64: =AG212 -> 0 | AH64: =SUM(C64:AG64) -> 0
A65: 水炉耗标煤量 （吨） | C65: =C355 -> 0 | D65: =D355 -> 0 | E65: =E355 -> 0 | F65: =F355 -> 0 | G65: =G355 -> 0 | H65: =H355 -> 0 | I65: =I355 -> 0 | J65: =J355 -> 0 | ... AG65: =AG355 -> 235.33643 | AH65: =SUM(C65:AG65) -> 1395.8104
C66: =C356 -> 0 | D66: =D356 -> 0 | E66: =E356 -> 0 | F66: =F356 -> 0 | G66: =G356 -> 0 | H66: =H356 -> 0 | I66: =I356 -> 0 | J66: =J356 -> 0 | ... AG66: =AG356 -> 0 | AH66: =SUM(C66:AG66) -> 563.95728
B67: 计划值 | C67: =C357 -> 0 | D67: =D357 -> 0 | E67: =E357 -> 0 | F67: =F357 -> 0 | G67: =G357 -> 0 | H67: =H357 -> 0 | I67: =I357 -> 0 | J67: =J357 -> 0 | ... AG67: =AG357 -> 187.1045 | AH67: =SUM(C67:AG67) -> 1279.7948
B68: 与计划差值 | C68: =C358 -> 0 | D68: =D358 -> 0 | E68: =E358 -> 0 | F68: =F358 -> 0 | G68: =G358 -> 0 | H68: =H358 -> 0 | I68: =I358 -> 0 | J68: =J358 -> 0 | ... AG68: =AG358 -> -187.1045 | AH68: =SUM(C68:AG68) -> -715.8375
B69: 同比差值 | C69: =C359 -> 0 | D69: =D359 -> 0 | E69: =E359 -> 0 | F69: =F359 -> 0 | G69: =G359 -> 0 | H69: =H359 -> 0 | I69: =I359 -> 0 | J69: =J359 -> 0 | ... AG69: =AG359 -> -235.33643 | AH69: =SUM(C69:AG69) -> -831.85308
A70: 耗天然气量 （立方米） | C70: =C444 -> 0 | D70: =D444 -> 0 | E70: =E444 -> 0 | F70: =F444 -> 0 | G70: =G444 -> 0 | H70: =H444 -> 0 | I70: =I444 -> 0 | J70: =J444 -> 0 | ... AG70: =AG444 -> 0 | AH70: =SUM(C70:AG70) -> 0
C71: =C445 -> 0 | D71: =D445 -> 0 | E71: =E445 -> 0 | F71: =F445 -> 0 | G71: =G445 -> 0 | H71: =H445 -> 0 | I71: =I445 -> 0 | J71: =J445 -> 0 | ... AG71: =AG445 -> 0 | AH71: =SUM(C71:AG71) -> 0
B72: 计划值 | C72: =C445 -> 0 | D72: =D445 -> 0 | E72: =E445 -> 0 | F72: =F445 -> 0 | G72: =G445 -> 0 | H72: =H445 -> 0 | I72: =I445 -> 0 | J72: =J445 -> 0 | ... AG72: =AG445 -> 0 | AH72: =SUM(C72:AG72) -> 0
B73: 与计划差值 | C73: =C71-C72 -> 0 | D73: =D71-D72 -> 0 | E73: =E71-E72 -> 0 | F73: =F71-F72 -> 0 | G73: =G71-G72 -> 0 | H73: =H71-H72 -> 0 | I73: =I71-I72 -> 0 | J73: =J71-J72 -> 0 | ... AG73: =AG71-AG72 -> 0 | AH73: =SUM(C73:AG73) -> 0
B74: 同比差值 | C74: =C71-C70 -> 0 | D74: =D71-D70 -> 0 | E74: =E71-E70 -> 0 | F74: =F71-F70 -> 0 | G74: =G71-G70 -> 0 | H74: =H71-H70 -> 0 | I74: =I71-I70 -> 0 | J74: =J71-J70 -> 0 | ... AG74: =AG71-AG70 -> 0 | AH74: =SUM(C74:AG74) -> 0
A75: 总自来水量 （吨） | C75: =C221 -> 0 | D75: =D221 -> 0 | E75: =E221 -> 0 | F75: =F221 -> 0 | G75: =G221 -> 0 | H75: =H221 -> 0 | I75: =I221 -> 0 | J75: =J221 -> 0 | ... AG75: =AG221 -> 0 | AH75: =SUM(C75:AG75) -> 0
C76: =C219 -> 278 | D76: =D219 -> 340 | E76: =E219 -> 298 | F76: =F219 -> 287 | G76: =G219 -> 267 | H76: =H219 -> 234 | I76: =I219 -> 232 | J76: =J219 -> 307 | ... AG76: =AG219 -> 0 | AH76: =SUM(C76:AG76) -> 14102
B77: 同比差值 | C77: =C76-C75 -> 278 | D77: =D76-D75 -> 340 | E77: =E76-E75 -> 298 | F77: =F76-F75 -> 287 | G77: =G76-G75 -> 267 | H77: =H76-H75 -> 234 | I77: =I76-I75 -> 232 | J77: =J76-J75 -> 307 | ... AG77: =AG76-AG75 -> 0 | AH77: =SUM(C77:AG77) -> 14102
A78: 再生水量 （吨） | C78: =C226+C365 -> 0 | D78: =D226+D365 -> 0 | E78: =E226+E365 -> 0 | F78: =F226+F365 -> 0 | G78: =G226+G365 -> 0 | H78: =H226+H365 -> 0 | I78: =I226+I365 -> 0 | J78: =J226+J365 -> 0 | ... AG78: =AG226+AG365 -> 2121 | AH78: =SUM(C78:AG78) -> 31569
C79: =C227 -> 0 | D79: =D227 -> 0 | E79: =E227 -> 0 | F79: =F227 -> 0 | G79: =G227 -> 0 | H79: =H227 -> 0 | I79: =I227 -> 0 | J79: =J227 -> 0 | ... AG79: =AG227 -> 0 | AH79: =SUM(C79:AG79) -> 30039
B80: 同比差值 | C80: =C79-C78 -> 0 | D80: =D79-D78 -> 0 | E80: =E79-E78 -> 0 | F80: =F79-F78 -> 0 | G80: =G79-G78 -> 0 | H80: =H79-H78 -> 0 | I80: =I79-I78 -> 0 | J80: =J79-J78 -> 0 | ... AG80: =AG79-AG78 -> -2121 | AH80: =SUM(C80:AG80) -> -1530
A81: 电厂耗水量 （吨） | C81: =C221 -> 0 | D81: =D221 -> 0 | E81: =E221 -> 0 | F81: =F221 -> 0 | G81: =G221 -> 0 | H81: =H221 -> 0 | I81: =I221 -> 0 | J81: =J221 -> 0 | ... AG81: =AG221 -> 0 | AH81: =SUM(C81:AG81) -> 0
C82: =C222 -> 278 | D82: =D222 -> 340 | E82: =E222 -> 298 | F82: =F222 -> 287 | G82: =G222 -> 267 | H82: =H222 -> 234 | I82: =I222 -> 232 | J82: =J222 -> 307 | ... AG82: =AG222 -> 0 | AH82: =SUM(C82:AG82) -> 11703
B83: 计划值 | C83: =C223 -> 0 | D83: =D223 -> 0 | E83: =E223 -> 0 | F83: =F223 -> 0 | G83: =G223 -> 0 | H83: =H223 -> 0 | I83: =I223 -> 0 | J83: =J223 -> 0 | ... AG83: =AG223 -> 0 | AH83: =SUM(C83:AG83) -> 0
B84: 与计划差值 | C84: =C224 -> 278 | D84: =D224 -> 340 | E84: =E224 -> 298 | F84: =F224 -> 287 | G84: =G224 -> 267 | H84: =H224 -> 234 | I84: =I224 -> 232 | J84: =J224 -> 307 | ... AG84: =AG224 -> 0 | AH84: =SUM(C84:AG84) -> 11703
B85: 同比差值 | C85: =C225 -> 278 | D85: =D225 -> 340 | E85: =E225 -> 298 | F85: =F225 -> 287 | G85: =G225 -> 267 | H85: =H225 -> 234 | I85: =I225 -> 232 | J85: =J225 -> 307 | ... AG85: =AG225 -> 0 | AH85: =SUM(C85:AG85) -> 11703
A86: 耗柴油量 （吨） | C86: =C229+C373 -> 0 | D86: =D229+D373 -> 0 | E86: =E229+E373 -> 0 | F86: =F229+F373 -> 0 | G86: =G229+G373 -> 0 | H86: =H229+H373 -> 0 | I86: =I229+I373 -> 0 | J86: =J229+J373 -> 0 | ... AG86: =AG229+AG373 -> 0 | AH86: =SUM(C86:AG86) -> 3.6
C87: =C230+C373 -> 0 | D87: =D230+D374 -> 0 | E87: =E230+E374 -> 0 | F87: =F230+F374 -> 0 | G87: =G230+G374 -> 0 | H87: =H230+H374 -> 0 | I87: =I230+I374 -> 0 | J87: =J230+J374 -> 0 | K87: =K230+K374 -> 0 | ... AG87: =AG230+AG374 -> 0 | AH87: =SUM(C87:AG87) -> 3.6
B88: 计划值 | C88: =C231+C375 -> 0 | D88: =D231+D375 -> 0 | E88: =E231+E375 -> 0 | F88: =F231+F375 -> 0 | G88: =G231+G375 -> 0 | H88: =H231+H375 -> 0 | I88: =I231+I375 -> 0 | J88: =J231+J375 -> 0 | ... AG88: =AG231+AG375 -> 0 | AH88: =SUM(C88:AG88) -> 5
B89: 与计划差值 | C89: =C87-C88 -> 0 | D89: =D87-D88 -> 0 | E89: =E87-E88 -> 0 | F89: =F87-F88 -> 0 | G89: =G87-G88 -> 0 | H89: =H87-H88 -> 0 | I89: =I87-I88 -> 0 | J89: =J87-J88 -> 0 | ... AG89: =AG87-AG88 -> 0 | AH89: =SUM(C89:AG89) -> -1.4
B90: 同比差值 | C90: =C87-C86 -> 0 | D90: =D87-D86 -> 0 | E90: =E87-E86 -> 0 | F90: =F87-F86 -> 0 | G90: =G87-G86 -> 0 | H90: =H87-H86 -> 0 | I90: =I87-I86 -> 0 | J90: =J87-J86 -> 0 | ... AG90: =AG87-AG86 -> 0 | AH90: =SUM(C90:AG90) -> 0
A91: 外购电量 （千万时） | C91: =C234 -> 0.48 | D91: =D234 -> 0.54 | E91: =E234 -> 0.54 | F91: =F234 -> 0.6 | G91: =G234 -> 0.54 | H91: =H234 -> 0.6 | I91: =I234 -> 0.54 | J91: =J234 -> 0.72 | ... AG91: =AG234 -> 6.19975 | AH91: =SUM(C91:AG91) -> 84.709338
C92: =C235 -> 0.54 | D92: =D235 -> 0.54 | E92: =E235 -> 0.54 | F92: =F235 -> 0.54 | G92: =G235 -> 0.54 | H92: =H235 -> 0.54 | I92: =I235 -> 0.48 | J92: =J235 -> 0.72 | ... AG92: =AG235 -> 0 | AH92: =SUM(C92:AG92) -> 54.96
B93: 计划值 | C93: =C236 -> 0 | D93: =D236 -> 0 | E93: =E236 -> 0 | F93: =F236 -> 0 | G93: =G236 -> 0 | H93: =H236 -> 0 | I93: =I236 -> 0 | J93: =J236 -> 0 | ... AG93: =AG236 -> 0 | AH93: =SUM(C93:AG93) -> 0
B94: 与计划差值 | C94: =C237 -> 0.54 | D94: =D237 -> 0.54 | E94: =E237 -> 0.54 | F94: =F237 -> 0.54 | G94: =G237 -> 0.54 | H94: =H237 -> 0.54 | I94: =I237 -> 0.48 | J94: =J237 -> 0.72 | ... AG94: =AG237 -> 0 | AH94: =SUM(C94:AG94) -> 54.96
B95: 同比差值 | C95: =C238 -> 0.06 | D95: =D238 -> 0 | E95: =E238 -> 0 | F95: =F238 -> -0.06 | G95: =G238 -> 0 | H95: =H238 -> -0.06 | I95: =I238 -> -0.06 | J95: =J238 -> 0 | ... AG95: =AG238 -> -6.19975 | AH95: =SUM(C95:AG95) -> -29.749338
A96: 石灰石 (含水炉）（吨） | C96: =C241+C383 -> 0 | D96: =D241+D383 -> 0 | E96: =E241+E383 -> 0 | F96: =F241+F383 -> 0 | G96: =G241+G383 -> 0 | H96: =H241+H383 -> 0 | I96: =I241+I383 -> 0 | J96: =J241+J383 -> 0 | ... AG96: =AG241+AG383 -> 9.3 | AH96: =SUM(C96:AG96) -> 56.73
C97: =C242+C384 -> 0 | D97: =D242+D384 -> 0 | E97: =E242+E384 -> 0 | F97: =F242+F384 -> 0 | G97: =G242+G384 -> 0 | H97: =H242+H384 -> 0 | I97: =I242+I384 -> 0 | J97: =J242+J384 -> 0 | ... AG97: =AG242+AG384 -> 0 | AH97: =SUM(C97:AG97) -> 13.37
B98: 计划值 | C98: =C243+C385 -> 0 | D98: =D243+D385 -> 0 | E98: =E243+E385 -> 0 | F98: =F243+F385 -> 0 | G98: =G243+G385 -> 0 | H98: =H243+H385 -> 0 | I98: =I243+I385 -> 0 | J98: =J243+J385 -> 0 | ... AG98: =AG243+AG385 -> 6.7219576 | AH98: =SUM(C98:AG98) -> 45.97819
B99: 与计划差值 | C99: =C97-C98 -> 0 | D99: =D97-D98 -> 0 | E99: =E97-E98 -> 0 | F99: =F97-F98 -> 0 | G99: =G97-G98 -> 0 | H99: =H97-H98 -> 0 | I99: =I97-I98 -> 0 | J99: =J97-J98 -> 0 | ... AG99: =AG97-AG98 -> -6.7219576 | AH99: =SUM(C99:AG99) -> -32.60819
B100: 同比差值 | C100: =C97-C96 -> 0 | D100: =D97-D96 -> 0 | E100: =E97-E96 -> 0 | F100: =F97-F96 -> 0 | G100: =G97-G96 -> 0 | H100: =H97-H96 -> 0 | I100: =I97-I96 -> 0 | J100: =J97-J96 -> 0 | ... AG100: =AG97-AG96 -> -9.3 | AH100: =SUM(C100:AG100) -> -43.36
A101: 氨水 (含水炉） （吨） | C101: =C246+C388 -> 0 | D101: =D246+D388 -> 0 | E101: =E246+E388 -> 0 | F101: =F246+F388 -> 0 | G101: =G246+G388 -> 0 | H101: =H246+H388 -> 0 | I101: =I246+I388 -> 0 | J101: =J246+J388 -> 0 | ... AG101: =AG246+AG388 -> 1.49 | AH101: =SUM(C101:AG101) -> 10.63
C102: =C247+C389 -> 0 | D102: =D247+D389 -> 0 | E102: =E247+E389 -> 0 | F102: =F247+F389 -> 0 | G102: =G247+G389 -> 0 | H102: =H247+H389 -> 0 | I102: =I247+I389 -> 0 | J102: =J247+J389 -> 0 | ... AG102: =AG247+AG389 -> 0 | AH102: =SUM(C102:AG102) -> 4.57
...

Sheet 2026.11
A1: 生产指标 | B1: 统计时间 | C1: 46327 | D1: 46328 | E1: 46329 | F1: 46330 | G1: 46331 | H1: 46332 | I1: 46333 | J1: 46334 | K1: 46335 | L1: 46336 | M1: 46337 | N1: 46338 | O1: 46339 | P1: 46340 | Q1: 46341 | R1: 46342 | S1: 46343 | T1: 46344 | U1: 46345 | V1: 46346 | W1: 46347 | X1: 46348 | Y1: 46349 | Z1: 46350 | AA1: 46351 | AB1: 46352 | AC1: 46353 | AD1: 46354 | AE1: 46355 | AF1: 46356 | AG1: 46357 | AJ1: E | AU1: =U129 -> 0
A2: 天气 | B2: 2025 当日最低温度 | C2: 4 | D2: 3 | E2: 3 | F2: 12 | G2: 12 | H2: 9 | I2: 9 | J2: 11 | K2: 5 | L2: -4 | M2: -5 | N2: 0 | O2: 7 | P2: -1 | Q2: 7 | R2: 2 | S2: 2 | T2: 2 | U2: 2 | V2: 4 | W2: 9 | X2: 8 | Y2: 7 | Z2: 0 | AA2: 1 | AB2: 0 | AC2: 0 | AD2: 4 | AE2: 5 | AF2: -1
B3: 2025 当日最高温度 | C3: 16 | D3: 8 | E3: 13 | F3: 16 | G3: 16 | H3: 16 | I3: 16 | J3: 16 | K3: 13 | L3: 15 | M3: 13 | N3: 18 | O3: 13 | P3: 12 | Q3: 17 | R3: 13 | S3: 4 | T3: 6 | U3: 13 | V3: 11 | W3: 15 | X3: 14 | Y3: 14 | Z3: 12 | AA3: 7 | AB3: 11 | AC3: 6 | AD3: 12 | AE3: 13 | AF3: 13
B4: 2025 气象 | C4: 晴 西北风5级 | D4: 晴 北风5级 | E4: 晴 南风4级 | F4: 晴 南风3级 | G4: 多云转晴 西风3级 | H4: 多云转晴 西风3级 | I4: 多云转阴 西风3级 | J4: 多云转晴 西风4级 | K4: 雾 西北风5级 | L4: 晴 西风3级 | M4: 晴 南风2级 | N4: 雾转晴 西风4级 | O4: 晴 北风4级 | P4: 晴 东南风2级 | Q4: 晴转多云 西南风3级 | R4: 晴 西北风5级 | S4: 阴 西北风5级 | T4: 晴 西北风5级 | U4: 晴 西南风2级 | V4: 晴 北风4级 | W4: 晴 西南风4级 | X4: 霾 西南风4级 | Y4: 多云 北风5级 | Z4: 阴转雨夹雪 北风5级 | AA4: 晴 北风5级 | AB4: 多云转阴 西南风5级 | AC4: 晴 北风5级 | AD4: 晴 南风5级 | AE4: 晴 南风5级 | AF4: 多云转晴 西北风5级
B5: 2026 当日最低温度
B6: 2026 当日最高温度
B7: 2026 气象
A8: 汇总
A9: 运行方式 炉/机 | Q9: 轻度雾霾转阴 | R9: 24℃ | S9: 14℃ | T9: 西北风1级 | AU9: =AO155 -> 0
Q10: 多云 | R10: 21℃ | S10: 16℃ | T10: 东南风3级 | AU10: =U147 -> 0.952076
B11: 计划 | Q11: 阴偶有小雨转大雨 | R11: 23℃ | S11: 15℃ | T11: 南风5级 | AU11: =AO147 -> 0
A12: 发电量 （万千万时) | C12: =C173 -> 2.016 | D12: =D173 -> 20.448 | E12: =E173 -> 49.728 | F12: =F173 -> 47.28 | G12: =G173 -> 46.992 | H12: =H173 -> 53.76 | I12: =I173 -> 48.384 | J12: =J173 -> 77.376 | ... O12: =O173 -> 111.792 | Q12: 阴转多云 | R12: 21℃ | S12: 13℃ | T12: 东北风2级 | U12: =U173 -> 116.448 | V12: =V173 -> 117.744 | W12: =W173 -> 129.648 | X12: =X173 -> 128.832 | Y12: =Y173 -> 127.344 | Z12: =Z173 -> 140.064 | AA12: =AA173 -> 180.24 | AB12: =AB173 -> 169.872 | ... AG12: =AG173 -> 0 | AH12: =SUM(C12:AG12) -> 2633.664 | AU12: =U186 -> 1.74
C13: =C174 -> 0 | D13: =D174 -> 0 | E13: =E174 -> 0 | F13: =F174 -> 0 | G13: =G174 -> 0 | H13: =H174 -> 0 | I13: =I174 -> 0 | J13: =J174 -> 0 | ... O13: =O174 -> 0 | Q13: 阴 | R13: 20℃ | S13: 13℃ | T13: 东风1级 | U13: =U174 -> 0 | V13: =V174 -> 0 | W13: =W174 -> 0 | X13: =X174 -> 0 | Y13: =Y174 -> 0 | Z13: =Z174 -> 0 | AA13: =AA174 -> 0 | AB13: =AB174 -> 0 | ... AG13: =AG174 -> 0 | AH13: =SUM(C13:AG13) -> 0 | AU13: =AO188 -> 0
B14: 计划值 | C14: =C175 -> 0 | D14: =D175 -> 0 | E14: =E175 -> 0 | F14: =F175 -> 0 | G14: =G175 -> 0 | H14: =H175 -> 0 | I14: =I175 -> 0 | J14: =J175 -> 0 | ... AG14: =AG175 -> 0 | AH14: =SUM(C14:AG14) -> 0 | AU14: =U181 -> 0
B15: 与计划差值 | C15: =C176 -> 0 | D15: =D176 -> 0 | E15: =E176 -> 0 | F15: =F176 -> 0 | G15: =G176 -> 0 | H15: =H176 -> 0 | I15: =I176 -> 0 | J15: =J176 -> 0 | ... AG15: =AG176 -> 0 | AH15: =SUM(C15:AG15) -> 0 | AU15: =AO181 -> 0
B16: 同比差值 | C16: =C177 -> -2.016 | D16: =D177 -> -20.448 | E16: =E177 -> -49.728 | F16: =F177 -> -47.28 | G16: =G177 -> -46.992 | H16: =H177 -> -53.76 | I16: =I177 -> -48.384 | J16: =J177 -> -77.376 | ... AG16: =AG177 -> 0 | AH16: =SUM(C16:AG16) -> -3339.792 | AU16: =U189 -> #DIV/0!
A17: 上网供电量 （万千万时) | C17: =C178 -> 1.6371 | D17: =D178 -> 13.9574 | E17: =E178 -> 32.7096 | F17: =F178 -> 28.512 | G17: =G178 -> 18.216 | H17: =H178 -> 23.6016 | I17: =I178 -> 17.8525 | J17: =J178 -> 44.2728 | ... AG17: =AG178 -> 0 | AH17: =SUM(C17:AG17) -> 2257.9374 | AU17: =AO191 -> 0
C18: =C179 -> 0 | D18: =D179 -> 0 | E18: =E179 -> 0 | F18: =F179 -> 0 | G18: =G179 -> 0 | H18: =H179 -> 0 | I18: =I179 -> 0 | J18: =J179 -> 0 | ... AG18: =AG179 -> 0 | AH18: =SUM(C18:AG18) -> 0 | AU18: =U192 -> #DIV/0!
B19: 计划值 | C19: =C180 -> 0 | D19: =D180 -> 0 | E19: =E180 -> 0 | F19: =F180 -> 0 | G19: =G180 -> 0 | H19: =H180 -> 0 | I19: =I180 -> 0 | J19: =J180 -> 0 | ... AG19: =AG180 -> 0 | AH19: =SUM(C19:AG19) -> 0 | AU19: =AO194 -> 0
B20: 与计划差值 | C20: =C181 -> 0 | D20: =D181 -> 0 | E20: =E181 -> 0 | F20: =F181 -> 0 | G20: =G181 -> 0 | H20: =H181 -> 0 | I20: =I181 -> 0 | J20: =J181 -> 0 | ... AG20: =AG181 -> 0 | AH20: =SUM(C20:AG20) -> 0 | AU20: =AU2/((AU4-AU21)*U137/1000) -> #DIV/0!
B21: 同比差值 | C21: =C182 -> -1.6371 | D21: =D182 -> -13.9574 | E21: =E182 -> -32.7096 | F21: =F182 -> -28.512 | G21: =G182 -> -18.216 | H21: =H182 -> -23.6016 | I21: =I182 -> -17.8525 | J21: =J182 -> -44.2728 | ... AG21: =AG182 -> 0 | AH21: =SUM(C21:AG21) -> -2257.9374 | AU21: =U300 -> 0
A22: 综合厂 用电量 （万千万时) | C22: =C183 -> 0 | D22: =D183 -> 0 | E22: =E183 -> 0 | F22: =F183 -> 0 | G22: =G183 -> 0 | H22: =H183 -> 0 | I22: =I183 -> 0 | J22: =J183 -> 0 | ... AG22: =AG183 -> 0 | AH22: =SUM(C22:AG22) -> 0
C23: =C184 -> 0 | D23: =D184 -> 0 | E23: =E184 -> 0 | F23: =F184 -> 0 | G23: =G184 -> 0 | H23: =H184 -> 0 | I23: =I184 -> 0 | J23: =J184 -> 0 | ... AG23: =AG184 -> 0 | AH23: =SUM(C23:AG23) -> 43.86
B24: 计划值 | C24: =C185 -> 0 | D24: =D185 -> 0 | E24: =E185 -> 0 | F24: =F185 -> 0 | G24: =G185 -> 0 | H24: =H185 -> 0 | I24: =I185 -> 0 | J24: =J185 -> 0 | ... AG24: =AG185 -> 0 | AH24: =SUM(C24:AG24) -> 0
B25: 与计划差值 | C25: =C186 -> 0 | D25: =D186 -> 0 | E25: =E186 -> 0 | F25: =F186 -> 0 | G25: =G186 -> 0 | H25: =H186 -> 0 | I25: =I186 -> 0 | J25: =J186 -> 0 | ... AG25: =AG186 -> 0 | AH25: =SUM(C25:AG25) -> 43.86
B26: 同比差值 | C26: =C187 -> 0 | D26: =D187 -> 0 | E26: =E187 -> 0 | F26: =F187 -> 0 | G26: =G187 -> 0 | H26: =H187 -> 0 | I26: =I187 -> 0 | J26: =J187 -> 0 | ... AG26: =AG187 -> 0 | AH26: =SUM(C26:AG26) -> 43.86
A27: 综合 厂用电率 （%） | C27: =C188 -> 0 | D27: =D188 -> 0 | E27: =E188 -> 0 | F27: =F188 -> 0 | G27: =G188 -> 0 | H27: =H188 -> 0 | I27: =I188 -> 0 | J27: =J188 -> 0 | ... AF27: =AF188 -> 0 | AH27: =AH22/AH12 -> 0
C28: =C189 -> #DIV/0! | D28: =D189 -> #DIV/0! | E28: =E189 -> #DIV/0! | F28: =F189 -> #DIV/0! | G28: =G189 -> #DIV/0! | H28: =H189 -> #DIV/0! | I28: =I189 -> #DIV/0! | J28: =J189 -> #DIV/0! | ... AG28: =AG189 -> #DIV/0! | AH28: =AH23/AH13 -> #DIV/0!
B29: 计划值 | C29: =C190 -> 0 | D29: =D190 -> 0 | E29: =E190 -> 0 | F29: =F190 -> 0 | G29: =G190 -> 0 | H29: =H190 -> 0 | I29: =I190 -> 0 | J29: =J190 -> 0 | ... AH29: =AH190 -> 0
B30: 与计划差值 | C30: =C191 -> #DIV/0! | D30: =D191 -> #DIV/0! | E30: =E191 -> #DIV/0! | F30: =F191 -> #DIV/0! | G30: =G191 -> #DIV/0! | H30: =H191 -> #DIV/0! | I30: =I191 -> #DIV/0! | J30: =J191 -> #DIV/0! | ... AG30: =AG191 -> #DIV/0! | AH30: =SUM(C30:AG30) -> #DIV/0!
B31: 同比差值 | C31: =C192 -> #DIV/0! | D31: =D192 -> #DIV/0! | E31: =E192 -> #DIV/0! | F31: =F192 -> #DIV/0! | G31: =G192 -> #DIV/0! | H31: =H192 -> #DIV/0! | I31: =I192 -> #DIV/0! | J31: =J192 -> #DIV/0! | ... AG31: =AG192 -> #DIV/0! | AH31: =SUM(C31:AG31) -> #DIV/0!
A32: 外供汽量 (吨） | C32: =C193+C432 -> 0 | D32: =D193+D432 -> 0 | E32: =E193+E432 -> 0 | F32: =F193+F432 -> 0 | G32: =G193+G432 -> 0 | H32: =H193+H432 -> 0 | I32: =I193+I432 -> 0 | J32: =J193+J432 -> 0 | ... AG32: =AG193+AG432 -> 0 | AH32: =SUM(C32:AG32) -> 10162.8
C33: =C194 -> 0 | D33: =D194 -> 0 | E33: =E194 -> 0 | F33: =F194 -> 0 | G33: =G194 -> 0 | H33: =H194 -> 0 | I33: =I194 -> 0 | J33: =J194 -> 0 | ... AG33: =AG194 -> 0 | AH33: =SUM(C33:AG33) -> 0
B34: 计划值 | C34: =C195 -> 0 | D34: =D195 -> 0 | E34: =E195 -> 0 | F34: =F195 -> 0 | G34: =G195 -> 0 | H34: =H195 -> 0 | I34: =I195 -> 0 | J34: =J195 -> 0 | ... AG34: =AG195 -> 0 | AH34: =SUM(C34:AG34) -> 0
B35: 与计划差值 | C35: =C33-C34 -> 0 | D35: =D33-D34 -> 0 | E35: =E33-E34 -> 0 | F35: =F33-F34 -> 0 | G35: =G33-G34 -> 0 | H35: =H33-H34 -> 0 | I35: =I33-I34 -> 0 | J35: =J33-J34 -> 0 | ... AG35: =AG33-AG34 -> 0 | AH35: =SUM(C35:AG35) -> 0
B36: 同比差值 | C36: =C33-C32 -> 0 | D36: =D33-D32 -> 0 | E36: =E33-E32 -> 0 | F36: =F33-F32 -> 0 | G36: =G33-G32 -> 0 | H36: =H33-H32 -> 0 | I36: =I33-I32 -> 0 | J36: =J33-J32 -> 0 | ... AG36: =AG33-AG32 -> 0 | AH36: =SUM(C36:AG36) -> -10162.8
A37: 供首站汽量 （吨） | C37: =C459+C475 -> 826 | D37: =D459+D475 -> 3008 | E37: =E459+E475 -> 3068 | F37: =F459+F475 -> 2806 | G37: =G459+G475 -> 3000 | H37: =H459+H475 -> 4897 | I37: =I459+I475 -> 2914 | J37: =J459+J475 -> 1149 | ... AG37: =AG459+AG475 -> 0 | AH37: =SUM(C37:AG37) -> 137945
C40: =C460+C476 -> 0 | D40: =D460+D476 -> 0 | E40: =E460+E476 -> 0 | F40: =F460+F476 -> 0 | G40: =G460+G476 -> 0 | H40: =H460+H476 -> 0 | I40: =I460+I476 -> 0 | J40: =J460+J476 -> 0 | ... AG40: =AG460+AG476 -> 0 | AH40: =SUM(C40:AG40) -> 0
B41: 同比差值 | C41: =C40-C37 -> -826 | D41: =D40-D37 -> -3008 | E41: =E40-E37 -> -3068 | F41: =F40-F37 -> -2806 | G41: =G40-G37 -> -3000 | H41: =H40-H37 -> -4897 | I41: =I40-I37 -> -2914 | J41: =J40-J37 -> -1149 | ... AG41: =AG40-AG37 -> 0 | AH41: =SUM(C41:AG41) -> -137945
A42: 天然气炉 供汽量 （吨） | C42: =C432 -> 0 | D42: =D432 -> 0 | E42: =E432 -> 0 | F42: =F432 -> 0 | G42: =G432 -> 0 | H42: =H432 -> 0 | I42: =I432 -> 0 | J42: =J432 -> 0 | ... AG42: =AG432 -> 0 | AH42: =SUM(C42:AG42) -> 0
C43: =C433 -> 0 | D43: =D433 -> 0 | E43: =E433 -> 0 | F43: =F433 -> 0 | G43: =G433 -> 0 | H43: =H433 -> 0 | I43: =I433 -> 0 | J43: =J433 -> 0 | ... AG43: =AG433 -> 0 | AH43: =SUM(C43:AG43) -> 0
B44: 同比差值 | C44: =C43-C42 -> 0 | D44: =D43-D42 -> 0 | E44: =E43-E42 -> 0 | F44: =F43-F42 -> 0 | G44: =G43-G42 -> 0 | H44: =H43-H42 -> 0 | I44: =I43-I42 -> 0 | J44: =J43-J42 -> 0 | ... AG44: =AG43-AG42 -> 0 | AH44: =SUM(C44:AG44) -> 0
A45: 外供热总量 （吉焦） | C45: =C33*2.951694+C500+C501+C498 -> 0 | AH45: =SUM(C45:AG45) -> 0
C46: =C33*2.951694+C346+C469+C498+C485 -> 0 | D46: =D33*2.951694+D346+D469+D498+D485 -> 0 | E46: =E33*2.951694+E346+E469+E498+E485 -> 0 | F46: =F33*2.951694+F346+F469+F498+F485 -> 0 | G46: =G33*2.951694+G346+G469+G498+G485 -> 0 | H46: =H33*2.951694+H346+H469+H498+H485 -> 0 | I46: =I33*2.951694+I346+I469+I498+I485 -> 0 | J46: =J33*2.951694+J346+J469+J498+J485 -> 0 | ... AG46: =AG33*2.951694+AG346+AG469+AG498+AG485 -> 0 | AH46: =SUM(C46:AG46) -> 15210
B47: 计划值 | C47: =C200+C347+C436 -> 0 | D47: =D200+D347+D436 -> 0 | E47: =E200+E347+E436 -> 0 | F47: =F200+F347+F436 -> 0 | G47: =G200+G347+G436 -> 0 | H47: =H200+H347+H436 -> 0 | I47: =I200+I347+I436 -> 0 | J47: =J200+J347+J436 -> 0 | ... AG47: =AG200+AG347+AG436 -> 0 | AH47: =SUM(C47:AG47) -> 0
B48: 与计划差值 | C48: =C46-C47 -> 0 | D48: =D46-D47 -> 0 | E48: =E46-E47 -> 0 | F48: =F46-F47 -> 0 | G48: =G46-G47 -> 0 | H48: =H46-H47 -> 0 | I48: =I46-I47 -> 0 | J48: =J46-J47 -> 0 | ... AG48: =AG46-AG47 -> 0 | AH48: =SUM(C48:AG48) -> 15210
B49: 同比差值 | C49: =C46-C45 -> 0 | D49: =D46-D45 -> 0 | E49: =E46-E45 -> 0 | F49: =F46-F45 -> 0 | G49: =G46-G45 -> 0 | H49: =H46-H45 -> 0 | I49: =I46-I45 -> 0 | J49: =J46-J45 -> 0 | ... AG49: =AG46-AG45 -> 0 | AH49: =SUM(C49:AG49) -> 15210
A50: 电厂耗原煤量 （吨） | C50: =C203 -> 292 | D50: =D203 -> 531 | E50: =E203 -> 585 | F50: =F203 -> 632 | G50: =G203 -> 716 | H50: =H203 -> 908 | I50: =I203 -> 609 | J50: =J203 -> 679 | ... AG50: =AG203 -> 0 | AH50: =SUM(C50:AG50) -> 34169
C51: =C204 -> 0 | D51: =D204 -> 0 | E51: =E204 -> 0 | F51: =F204 -> 0 | G51: =G204 -> 0 | H51: =H204 -> 0 | I51: =I204 -> 0 | J51: =J204 -> 0 | ... AG51: =AG204 -> 0 | AH51: =SUM(C51:AG51) -> 0
B52: 计划值 | C52: =C205 -> 0 | D52: =D205 -> 0 | E52: =E205 -> 0 | F52: =F205 -> 0 | G52: =G205 -> 0 | H52: =H205 -> 0 | I52: =I205 -> 0 | J52: =J205 -> 0 | ... AG52: =AG205 -> 0 | AH52: =SUM(C52:AG52) -> 0
B53: 与计划差值 | C53: =C206 -> 0 | D53: =D206 -> 0 | E53: =E206 -> 0 | F53: =F206 -> 0 | G53: =G206 -> 0 | H53: =H206 -> 0 | I53: =I206 -> 0 | J53: =J206 -> 0 | ... AG53: =AG206 -> 0 | AH53: =SUM(C53:AG53) -> 0
B54: 同比差值 | C54: =C207 -> -292 | D54: =D207 -> -531 | E54: =E207 -> -585 | F54: =F207 -> -632 | G54: =G207 -> -716 | H54: =H207 -> -908 | I54: =I207 -> -609 | J54: =J207 -> -679 | ... AG54: =AG207 -> 0 | AH54: =SUM(C54:AG54) -> -34169
A55: 水炉耗原煤量 （吨） | C55: =C350 -> 358 | D55: =D350 -> 389 | E55: =E350 -> 428 | F55: =F350 -> 492 | G55: =G350 -> 700 | H55: =H350 -> 444 | I55: =I350 -> 627 | J55: =J350 -> 619 | ... AG55: =AG350 -> 0 | AH55: =SUM(C55:AG55) -> 9019
C56: =C351 -> 0 | D56: =D351 -> 0 | E56: =E351 -> 0 | F56: =F351 -> 0 | G56: =G351 -> 0 | H56: =H351 -> 0 | I56: =I351 -> 0 | J56: =J351 -> 0 | ... AG56: =AG351 -> 0 | AH56: =SUM(C56:AG56) -> 935
B57: 计划值 | C57: =C352 -> 0 | D57: =D352 -> 0 | E57: =E352 -> 0 | F57: =F352 -> 0 | G57: =G352 -> 0 | H57: =H352 -> 0 | I57: =I352 -> 0 | J57: =J352 -> 0 | ... AG57: =AG352 -> 0 | AH57: =SUM(C57:AG57) -> 0
B58: 与计划差值 | C58: =C353 -> 0 | D58: =D353 -> 0 | E58: =E353 -> 0 | F58: =F353 -> 0 | G58: =G353 -> 0 | H58: =H353 -> 0 | I58: =I353 -> 0 | J58: =J353 -> 0 | ... AG58: =AG353 -> 0 | AH58: =SUM(C58:AG58) -> 935
B59: 同比差值 | C59: =C354 -> -358 | D59: =D354 -> -389 | E59: =E354 -> -428 | F59: =F354 -> -492 | G59: =G354 -> -700 | H59: =H354 -> -444 | I59: =I354 -> -627 | J59: =J354 -> -619 | ... AG59: =AG354 -> 0 | AH59: =SUM(C59:AG59) -> -8084
A60: 电厂耗标煤量 （吨） | C60: =C208 -> 213.8092 | D60: =D208 -> 387.36113 | E60: =E208 -> 432.1431 | F60: =F208 -> 468.58742 | G60: =G208 -> 507.17074 | H60: =H208 -> 646.57977 | I60: =I208 -> 455.48246 | J60: =J208 -> 496.02122 | ... AG60: =AG208 -> 0 | AH60: =SUM(C60:AG60) -> 24795.181
C61: =C209 -> 0 | D61: =D209 -> 0 | E61: =E209 -> 0 | F61: =F209 -> 0 | G61: =G209 -> 0 | H61: =H209 -> 0 | I61: =I209 -> 0 | J61: =J209 -> 0 | ... AG61: =AG209 -> 0 | AH61: =SUM(C61:AG61) -> 0
B62: 计划值 | C62: =C210 -> 0 | D62: =D210 -> 0 | E62: =E210 -> 0 | F62: =F210 -> 0 | G62: =G210 -> 0 | H62: =H210 -> 0 | I62: =I210 -> 0 | J62: =J210 -> 0 | ... AG62: =AG210 -> 0 | AH62: =SUM(C62:AG62) -> 0
B63: 与计划差值 | C63: =C211 -> 0 | D63: =D211 -> 0 | E63: =E211 -> 0 | F63: =F211 -> 0 | G63: =G211 -> 0 | H63: =H211 -> 0 | I63: =I211 -> 0 | J63: =J211 -> 0 | ... AG63: =AG211 -> 0 | AH63: =SUM(C63:AG63) -> 0
B64: 同比差值 | C64: =C212 -> -213.8092 | D64: =D212 -> -387.36113 | E64: =E212 -> -432.1431 | F64: =F212 -> -468.58742 | G64: =G212 -> -507.17074 | H64: =H212 -> -646.57977 | I64: =I212 -> -455.48246 | J64: =J212 -> -496.02122 | ... AG64: =AG212 -> 0 | AH64: =SUM(C64:AG64) -> -24795.181
A65: 水炉耗标煤量 （吨） | C65: =C355 -> 273.98458 | D65: =D355 -> 287.09124 | E65: =E355 -> 315.14399 | F65: =F355 -> 348.33493 | G65: =G355 -> 514.70588 | H65: =H355 -> 317.9869 | I65: =I355 -> 454.1835 | J65: =J355 -> 443.95319 | ... AG65: =AG355 -> 0 | AH65: =SUM(C65:AG65) -> 6534.0781
C66: =C356 -> 0 | D66: =D356 -> 0 | E66: =E356 -> 0 | F66: =F356 -> 0 | G66: =G356 -> 0 | H66: =H356 -> 0 | I66: =I356 -> 0 | J66: =J356 -> 0 | ... AG66: =AG356 -> 0 | AH66: =SUM(C66:AG66) -> 557.41948
B67: 计划值 | C67: =C357 -> 0 | D67: =D357 -> 0 | E67: =E357 -> 0 | F67: =F357 -> 0 | G67: =G357 -> 0 | H67: =H357 -> 0 | I67: =I357 -> 0 | J67: =J357 -> 0 | ... AG67: =AG357 -> 0 | AH67: =SUM(C67:AG67) -> 0
B68: 与计划差值 | C68: =C358 -> 0 | D68: =D358 -> 0 | E68: =E358 -> 0 | F68: =F358 -> 0 | G68: =G358 -> 0 | H68: =H358 -> 0 | I68: =I358 -> 0 | J68: =J358 -> 0 | ... AG68: =AG358 -> 0 | AH68: =SUM(C68:AG68) -> 557.41948
B69: 同比差值 | C69: =C359 -> -273.98458 | D69: =D359 -> -287.09124 | E69: =E359 -> -315.14399 | F69: =F359 -> -348.33493 | G69: =G359 -> -514.70588 | H69: =H359 -> -317.9869 | I69: =I359 -> -454.1835 | J69: =J359 -> -443.95319 | ... AG69: =AG359 -> 0 | AH69: =SUM(C69:AG69) -> -5976.6586
A70: 耗天然气量 （立方米） | C70: =C444 -> 0 | D70: =D444 -> 0 | E70: =E444 -> 0 | F70: =F444 -> 0 | G70: =G444 -> 0 | H70: =H444 -> 0 | I70: =I444 -> 0 | J70: =J444 -> 0 | ... AG70: =AG444 -> 0 | AH70: =SUM(C70:AG70) -> 0
C71: =C445 -> 0 | D71: =D445 -> 0 | E71: =E445 -> 0 | F71: =F445 -> 0 | G71: =G445 -> 0 | H71: =H445 -> 0 | I71: =I445 -> 0 | J71: =J445 -> 0 | ... AG71: =AG445 -> 0 | AH71: =SUM(C71:AG71) -> 0
B72: 计划值 | C72: =C445 -> 0 | D72: =D445 -> 0 | E72: =E445 -> 0 | F72: =F445 -> 0 | G72: =G445 -> 0 | H72: =H445 -> 0 | I72: =I445 -> 0 | J72: =J445 -> 0 | ... AG72: =AG445 -> 0 | AH72: =SUM(C72:AG72) -> 0
B73: 与计划差值 | C73: =C71-C72 -> 0 | D73: =D71-D72 -> 0 | E73: =E71-E72 -> 0 | F73: =F71-F72 -> 0 | G73: =G71-G72 -> 0 | H73: =H71-H72 -> 0 | I73: =I71-I72 -> 0 | J73: =J71-J72 -> 0 | ... AG73: =AG71-AG72 -> 0 | AH73: =SUM(C73:AG73) -> 0
B74: 同比差值 | C74: =C71-C70 -> 0 | D74: =D71-D70 -> 0 | E74: =E71-E70 -> 0 | F74: =F71-F70 -> 0 | G74: =G71-G70 -> 0 | H74: =H71-H70 -> 0 | I74: =I71-I70 -> 0 | J74: =J71-J70 -> 0 | ... AG74: =AG71-AG70 -> 0 | AH74: =SUM(C74:AG74) -> 0
A75: 总自来水量 （吨） | C75: =C221 -> 3233 | D75: =D221 -> 3882 | E75: =E221 -> 1806 | F75: =F221 -> 2623 | G75: =G221 -> 3059 | H75: =H221 -> 4297 | I75: =I221 -> 3004 | J75: =J221 -> 4308 | ... AG75: =AG221 -> 0 | AH75: =SUM(C75:AG75) -> 102306
C76: =C219 -> 0 | D76: =D219 -> 0 | E76: =E219 -> 0 | F76: =F219 -> 0 | G76: =G219 -> 0 | H76: =H219 -> 0 | I76: =I219 -> 0 | J76: =J219 -> 0 | ... AG76: =AG219 -> 0 | AH76: =SUM(C76:AG76) -> 10168
B77: 同比差值 | C77: =C76-C75 -> -3233 | D77: =D76-D75 -> -3882 | E77: =E76-E75 -> -1806 | F77: =F76-F75 -> -2623 | G77: =G76-G75 -> -3059 | H77: =H76-H75 -> -4297 | I77: =I76-I75 -> -3004 | J77: =J76-J75 -> -4308 | ... AG77: =AG76-AG75 -> 0 | AH77: =SUM(C77:AG77) -> -92138
A78: 再生水量 （吨） | C78: =C226+C365 -> 3537 | D78: =D226+D365 -> 3359 | E78: =E226+E365 -> 2985 | F78: =F226+F365 -> 2709 | G78: =G226+G365 -> 3264 | H78: =H226+H365 -> 3524 | I78: =I226+I365 -> 2715 | J78: =J226+J365 -> 3433 | ... AG78: =AG226+AG365 -> 0 | AH78: =SUM(C78:AG78) -> 96635
C79: =C227 -> 0 | D79: =D227 -> 0 | E79: =E227 -> 0 | F79: =F227 -> 0 | G79: =G227 -> 0 | H79: =H227 -> 0 | I79: =I227 -> 0 | J79: =J227 -> 0 | ... AG79: =AG227 -> 0 | AH79: =SUM(C79:AG79) -> 30039
B80: 同比差值 | C80: =C79-C78 -> -3537 | D80: =D79-D78 -> -3359 | E80: =E79-E78 -> -2985 | F80: =F79-F78 -> -2709 | G80: =G79-G78 -> -3264 | H80: =H79-H78 -> -3524 | I80: =I79-I78 -> -2715 | J80: =J79-J78 -> -3433 | ... AG80: =AG79-AG78 -> 0 | AH80: =SUM(C80:AG80) -> -66596
A81: 电厂耗水量 （吨） | C81: =C221 -> 3233 | D81: =D221 -> 3882 | E81: =E221 -> 1806 | F81: =F221 -> 2623 | G81: =G221 -> 3059 | H81: =H221 -> 4297 | I81: =I221 -> 3004 | J81: =J221 -> 4308 | ... AG81: =AG221 -> 0 | AH81: =SUM(C81:AG81) -> 102306
C82: =C222 -> 0 | D82: =D222 -> 0 | E82: =E222 -> 0 | F82: =F222 -> 0 | G82: =G222 -> 0 | H82: =H222 -> 0 | I82: =I222 -> 0 | J82: =J222 -> 0 | ... AG82: =AG222 -> 0 | AH82: =SUM(C82:AG82) -> #VALUE!
B83: 计划值 | C83: =C223 -> 0 | D83: =D223 -> 0 | E83: =E223 -> 0 | F83: =F223 -> 0 | G83: =G223 -> 0 | H83: =H223 -> 0 | I83: =I223 -> 0 | J83: =J223 -> 0 | ... AG83: =AG223 -> 0 | AH83: =SUM(C83:AG83) -> 0
B84: 与计划差值 | C84: =C224 -> 0 | D84: =D224 -> 0 | E84: =E224 -> 0 | F84: =F224 -> 0 | G84: =G224 -> 0 | H84: =H224 -> 0 | I84: =I224 -> 0 | J84: =J224 -> 0 | ... AG84: =AG224 -> 0 | AH84: =SUM(C84:AG84) -> #VALUE!
B85: 同比差值 | C85: =C225 -> -3233 | D85: =D225 -> -3882 | E85: =E225 -> -1806 | F85: =F225 -> -2623 | G85: =G225 -> -3059 | H85: =H225 -> -4297 | I85: =I225 -> -3004 | J85: =J225 -> -4308 | ... AG85: =AG225 -> 0 | AH85: =SUM(C85:AG85) -> #VALUE!
A86: 耗柴油量 （吨） | C86: =C229+C373 -> 42.3 | D86: =D229+D373 -> 0 | E86: =E229+E373 -> 0.9 | F86: =F229+F373 -> 10.8 | G86: =G229+G373 -> 27.9 | H86: =H229+H373 -> 10.8 | I86: =I229+I373 -> 3.6 | J86: =J229+J373 -> 16.2 | ... AG86: =AG229+AG373 -> 0 | AH86: =SUM(C86:AG86) -> 196.2
C87: =C230+C373 -> 0 | D87: =D230+D374 -> 0 | E87: =E230+E374 -> 0 | F87: =F230+F374 -> 0 | G87: =G230+G374 -> 0 | H87: =H230+H374 -> 0 | I87: =I230+I374 -> 0 | J87: =J230+J374 -> 0 | K87: =K230+K374 -> 0 | ... AG87: =AG230+AG374 -> 0 | AH87: =SUM(C87:AG87) -> 3.6
B88: 计划值 | C88: =C231+C375 -> 0 | D88: =D231+D375 -> 0 | E88: =E231+E375 -> 0 | F88: =F231+F375 -> 0 | G88: =G231+G375 -> 0 | H88: =H231+H375 -> 0 | I88: =I231+I375 -> 0 | J88: =J231+J375 -> 0 | ... AG88: =AG231+AG375 -> 0 | AH88: =SUM(C88:AG88) -> 0
B89: 与计划差值 | C89: =C87-C88 -> 0 | D89: =D87-D88 -> 0 | E89: =E87-E88 -> 0 | F89: =F87-F88 -> 0 | G89: =G87-G88 -> 0 | H89: =H87-H88 -> 0 | I89: =I87-I88 -> 0 | J89: =J87-J88 -> 0 | ... AG89: =AG87-AG88 -> 0 | AH89: =SUM(C89:AG89) -> 3.6
B90: 同比差值 | C90: =C87-C86 -> -42.3 | D90: =D87-D86 -> 0 | E90: =E87-E86 -> -0.9 | F90: =F87-F86 -> -10.8 | G90: =G87-G86 -> -27.9 | H90: =H87-H86 -> -10.8 | I90: =I87-I86 -> -3.6 | J90: =J87-J86 -> -16.2 | ... AG90: =AG87-AG86 -> 0 | AH90: =SUM(C90:AG90) -> -192.6
A91: 外购电量 （千万时） | C91: =C234 -> 19.4333 | D91: =D234 -> 12.7694 | E91: =E234 -> 7.073352 | F91: =F234 -> 8.449848 | G91: =G234 -> 2.975544 | H91: =H234 -> 7.15176 | I91: =I234 -> 0.90288 | J91: =J234 -> 0 | ... AG91: =AG234 -> 0 | AH91: =SUM(C91:AG91) -> 58.756084
C92: =C235 -> 0 | D92: =D235 -> 0 | E92: =E235 -> 0 | F92: =F235 -> 0 | G92: =G235 -> 0 | H92: =H235 -> 0 | I92: =I235 -> 0 | J92: =J235 -> 0 | ... AG92: =AG235 -> 0 | AH92: =SUM(C92:AG92) -> 43.86
B93: 计划值 | C93: =C236 -> 0 | D93: =D236 -> 0 | E93: =E236 -> 0 | F93: =F236 -> 0 | G93: =G236 -> 0 | H93: =H236 -> 0 | I93: =I236 -> 0 | J93: =J236 -> 0 | ... AG93: =AG236 -> 0 | AH93: =SUM(C93:AG93) -> 0
B94: 与计划差值 | C94: =C237 -> 0 | D94: =D237 -> 0 | E94: =E237 -> 0 | F94: =F237 -> 0 | G94: =G237 -> 0 | H94: =H237 -> 0 | I94: =I237 -> 0 | J94: =J237 -> 0 | ... AG94: =AG237 -> 0 | AH94: =SUM(C94:AG94) -> 43.86
B95: 同比差值 | C95: =C238 -> -19.4333 | D95: =D238 -> -12.7694 | E95: =E238 -> -7.073352 | F95: =F238 -> -8.449848 | G95: =G238 -> -2.975544 | H95: =H238 -> -7.15176 | I95: =I238 -> -0.90288 | J95: =J238 -> 0 | ... AG95: =AG238 -> 0 | AH95: =SUM(C95:AG95) -> -14.896084
A96: 石灰石 (含水炉）（吨） | C96: =C241+C383 -> 69.57 | D96: =D241+D383 -> 30.02 | E96: =E241+E383 -> 29.2 | F96: =F241+F383 -> 36.53 | G96: =G241+G383 -> 39.43 | H96: =H241+H383 -> 31.83 | I96: =I241+I383 -> 33 | J96: =J241+J383 -> 38.6 | ... AG96: =AG241+AG383 -> 0 | AH96: =SUM(C96:AG96) -> 1197.98
C97: =C242+C384 -> 0 | D97: =D242+D384 -> 0 | E97: =E242+E384 -> 0 | F97: =F242+F384 -> 0 | G97: =G242+G384 -> 0 | H97: =H242+H384 -> 0 | I97: =I242+I384 -> 0 | J97: =J242+J384 -> 0 | ... AG97: =AG242+AG384 -> 0 | AH97: =SUM(C97:AG97) -> 13.37
B98: 计划值 | C98: =C243+C385 -> 0 | D98: =D243+D385 -> 0 | E98: =E243+E385 -> 0 | F98: =F243+F385 -> 0 | G98: =G243+G385 -> 0 | H98: =H243+H385 -> 0 | I98: =I243+I385 -> 0 | J98: =J243+J385 -> 0 | ... AG98: =AG243+AG385 -> 0 | AH98: =SUM(C98:AG98) -> 0
B99: 与计划差值 | C99: =C97-C98 -> 0 | D99: =D97-D98 -> 0 | E99: =E97-E98 -> 0 | F99: =F97-F98 -> 0 | G99: =G97-G98 -> 0 | H99: =H97-H98 -> 0 | I99: =I97-I98 -> 0 | J99: =J97-J98 -> 0 | ... AG99: =AG97-AG98 -> 0 | AH99: =SUM(C99:AG99) -> 13.37
B100: 同比差值 | C100: =C97-C96 -> -69.57 | D100: =D97-D96 -> -30.02 | E100: =E97-E96 -> -29.2 | F100: =F97-F96 -> -36.53 | G100: =G97-G96 -> -39.43 | H100: =H97-H96 -> -31.83 | I100: =I97-I96 -> -33 | J100: =J97-J96 -> -38.6 | ... AG100: =AG97-AG96 -> 0 | AH100: =SUM(C100:AG100) -> -1184.61
A101: 氨水 (含水炉） （吨） | C101: =C246+C388 -> 1.73 | D101: =D246+D388 -> 3.55 | E101: =E246+E388 -> 4.1 | F101: =F246+F388 -> 4.06 | G101: =G246+G388 -> 5.63 | H101: =H246+H388 -> 5.87 | I101: =I246+I388 -> 4.5 | J101: =J246+J388 -> 4.45 | ... AG101: =AG246+AG388 -> 0 | AH101: =SUM(C101:AG101) -> 216.74
C102: =C247+C389 -> 0 | D102: =D247+D389 -> 0 | E102: =E247+E389 -> 0 | F102: =F247+F389 -> 0 | G102: =G247+G389 -> 0 | H102: =H247+H389 -> 0 | I102: =I247+I389 -> 0 | J102: =J247+J389 -> 0 | ... AG102: =AG247+AG389 -> 0 | AH102: =SUM(C102:AG102) -> 4.57
...

Sheet Sheet2
A1: 生产指标 | B1: 统计时间 | C1: 45962 | D1: 45963 | E1: 45964 | F1: 45965 | G1: 45966 | H1: 45967 | I1: 45968 | J1: 45969 | K1: 45970 | L1: 45971 | M1: 45972 | N1: 45973 | O1: 45974 | P1: 45975 | Q1: 45976 | R1: 45977 | S1: 45978 | T1: 45979 | U1: 45980 | V1: 45981 | W1: 45982 | X1: 45983 | Y1: 45984 | Z1: 45985 | AA1: 45986 | AB1: 45987 | AC1: 45988 | AD1: 45989 | AE1: 45990 | AF1: 45991 | AI1: 45991 | AU1: =U129 -> 0
A2: 天气 | B2: 2024 当日最低温度 | C2: 15 | D2: 15 | E2: 7 | F2: 4 | G2: 4 | H2: 4 | I2: 12 | J2: 12 | K2: 12 | L2: 12 | M2: 12 | N2: 9 | O2: 10 | P2: 12 | Q2: 13 | R2: 5 | S2: 2 | T2: 0 | U2: 4 | V2: 8 | W2: 3 | X2: 1 | Y2: 1 | Z2: 7 | AA2: 6 | AB2: 0 | AC2: -1 | AD2: 1 | AE2: 2 | AF2: 5
B3: 2024 当日最高温度 | C3: 19 | D3: 19 | E3: 20 | F3: 9 | G3: 12 | H3: 10 | I3: 16 | J3: 14 | K3: 16 | L3: 17 | M3: 17 | N3: 13 | O3: 15 | P3: 16 | Q3: 15 | R3: 15 | S3: 7 | T3: 5 | U3: 11 | V3: 13 | W3: 12 | X3: 7 | Y3: 7 | Z3: 11 | AA3: 12 | AB3: 5 | AC3: 2 | AD3: 3 | AE3: 8 | AF3: 10
B4: 2024 气象 | C4: 小雨转晴 西南风2级 | D4: 多云 南风3级 | E4: 多云转晴西北风5-6级 | F4: 多云转晴西北风3级 | G4: 晴 北风5级 | H4: 多云 北风4级 | I4: 晴 微风 | J4: 多云 西南风2级 | K4: 多云 西南风4级 | L4: 阴 西南风4级 | M4: 晴 西风2级 | N4: 多云 西南风3级 | O4: 多云 西南风3级 | P4: 小雨 西南风3级 | Q4: 雾 东北风4级 | R4: 小雨 西南风3级 | S4: 晴 东北风4级 | T4: 晴 东北风5级 | U4: 多云 西南风3级 | V4: 多云 西风2级 | W4: 晴 西北风3级 | X4: 晴 北风4级 | Y4: 晴 东北风3级 | Z4: 多云 南风3级 | AA4: 中雨 西北风5级 | AB4: 小雪转阴 西北风6级 | AC4: 多云 西北风6级 | AD4: 多云 西北风7级 | AE4: 多云 西北风6级 | AF4: 晴转多云 西北风4级
B5: 2025 当日最低温度 | C5: 4 | D5: 3 | E5: 3 | F5: 12 | G5: 12 | H5: 9 | I5: 9 | J5: 11 | K5: 5 | L5: -4 | M5: -5 | N5: 0 | O5: 7 | P5: -1 | Q5: 7 | R5: 2 | S5: 2 | T5: 2 | U5: 2 | V5: 4 | W5: 9 | X5: 8 | Y5: 7 | Z5: 0 | AA5: 1 | AB5: 0 | AC5: 0 | AD5: 4 | AE5: 5 | AF5: -1
B6: 2025 当日最高温度 | C6: 16 | D6: 8 | E6: 13 | F6: 16 | G6: 16 | H6: 16 | I6: 16 | J6: 16 | K6: 13 | L6: 15 | M6: 13 | N6: 18 | O6: 13 | P6: 12 | Q6: 17 | R6: 13 | S6: 4 | T6: 6 | U6: 13 | V6: 11 | W6: 15 | X6: 14 | Y6: 14 | Z6: 12 | AA6: 7 | AB6: 11 | AC6: 6 | AD6: 12 | AE6: 13 | AF6: 13
B7: 2025 气象 | C7: 晴 西北风5级 | D7: 晴 北风5级 | E7: 晴 南风4级 | F7: 晴 南风3级 | G7: 多云转晴 西风3级 | H7: 多云转晴 西风3级 | I7: 多云转阴 西风3级 | J7: 多云转晴 西风4级 | K7: 雾 西北风5级 | L7: 晴 西风3级 | M7: 晴 南风2级 | N7: 雾转晴 西风4级 | O7: 晴 北风4级 | P7: 晴 东南风2级 | Q7: 晴转多云 西南风3级 | R7: 晴 西北风5级 | S7: 阴 西北风5级 | T7: 晴 西北风5级 | U7: 晴 西南风2级 | V7: 晴 北风4级 | W7: 晴 西南风4级 | X7: 霾 西南风4级 | Y7: 多云 北风5级 | Z7: 阴转雨夹雪 北风5级 | AA7: 晴 北风5级 | AB7: 多云转阴 西南风5级 | AC7: 晴 北风5级 | AD7: 晴 南风5级 | AE7: 晴 南风5级 | AF7: 多云转晴 西北风5级
A8: 汇总
A9: 运行方式 炉/机 | AU9: =AO155 -> 0
AU10: =U147 -> 87.013182
B11: 计划 | AU11: =AO147 -> 0
A12: 发电量 （万千万时) | C12: =C173 -> 12.672 | D12: =D173 -> 62.496 | E12: =E173 -> 76.896 | F12: =F173 -> 122.112 | G12: =G173 -> 118.128 | H12: =H173 -> 115.152 | I12: =I173 -> 117.216 | J12: =J173 -> 114.576 | ... AG12: =AG173 -> 0 | AH12: =SUM(C12:AG12) -> 3431.241 | AU12: =U186 -> 3.7502425
C13: =C174 -> 2.016 | D13: =D174 -> 20.448 | E13: =E174 -> 49.728 | F13: =F174 -> 47.28 | G13: =G174 -> 46.992 | H13: =H174 -> 53.76 | I13: =I174 -> 48.384 | J13: =J174 -> 77.376 | ... AG13: =AG174 -> 0 | AH13: =SUM(C13:AG13) -> 3339.792 | AU13: =AO188 -> 18072.864
B14: 计划值 | C14: =C175 -> 47.170418 | D14: =D175 -> 60.449039 | E14: =E175 -> 81.4255 | F14: =F175 -> 126.42248 | G14: =G175 -> 119.16309 | H14: =H175 -> 123.12162 | I14: =I175 -> 103.34149 | J14: =J175 -> 63.605843 | ... AG14: =AG175 -> 0 | AH14: =SUM(C14:AG14) -> 4378.0487 | AU14: =U181 -> -18.334663
B15: 与计划差值 | C15: =C176 -> -45.154418 | D15: =D176 -> -40.001038 | E15: =E176 -> -31.6975 | F15: =F176 -> -79.142484 | G15: =G176 -> -72.171087 | H15: =H176 -> -69.36162 | I15: =I176 -> -54.957487 | J15: =J176 -> 13.770157 | ... AG15: =AG176 -> 0 | AH15: =SUM(C15:AG15) -> -1038.2567 | AU15: =AO181 -> 121.776
B16: 同比差值 | C16: =C177 -> -10.656 | D16: =D177 -> -42.048 | E16: =E177 -> -27.168 | F16: =F177 -> -74.832 | G16: =G177 -> -71.136 | H16: =H177 -> -61.392 | I16: =I177 -> -68.832 | J16: =J177 -> -37.2 | ... AG16: =AG177 -> 0 | AH16: =SUM(C16:AG16) -> -91.449 | AU16: =U189 -> 0.33755153
A17: 上网供电量 （万千万时) | C17: =C178 -> 10.1376 | D17: =D178 -> 37.7784 | E17: =E178 -> 47.4408 | F17: =F178 -> 82.368 | G17: =G178 -> 79.128 | H17: =H178 -> 80.784 | I17: =I178 -> 82.8414 | J17: =J178 -> 80.6256 | ... AG17: =AG178 -> 0 | AH17: =SUM(C17:AG17) -> 2317.3974 | AU17: =AO191 -> 32771
C18: =C179 -> 1.6371 | D18: =D179 -> 13.9574 | E18: =E179 -> 32.7096 | F18: =F179 -> 28.512 | G18: =G179 -> 18.216 | H18: =H179 -> 23.6016 | I18: =I179 -> 17.8525 | J18: =J179 -> 44.2728 | ... AG18: =AG179 -> 0 | AH18: =SUM(C18:AG18) -> 2257.9374 | AU18: =U192 -> 0.017112726
B19: 计划值 | C19: =C180 -> 34.370254 | D19: =D180 -> 44.045587 | E19: =E180 -> 59.329876 | F19: =F180 -> 92.116479 | G19: =G180 -> 86.826992 | H19: =H180 -> 89.711337 | I19: =I180 -> 75.298741 | J19: =J180 -> 46.345761 | ... AG19: =AG180 -> 0 | AH19: =SUM(C19:AG19) -> 3190.0214 | AU19: =AO194 -> 2463
B20: 与计划差值 | C20: =C181 -> -32.733154 | D20: =D181 -> -30.088187 | E20: =E181 -> -26.620276 | F20: =F181 -> -63.604479 | G20: =G181 -> -68.610992 | H20: =H181 -> -66.109737 | I20: =I181 -> -57.446241 | J20: =J181 -> -2.0729611 | ... AG20: =AG181 -> 0 | AH20: =SUM(C20:AG20) -> -932.08401 | AU20: =AU2/((AU4-AU21)*U137/1000) -> #DIV/0!
B21: 同比差值 | C21: =C182 -> -8.5005 | D21: =D182 -> -23.821 | E21: =E182 -> -14.7312 | F21: =F182 -> -53.856 | G21: =G182 -> -60.912 | H21: =H182 -> -57.1824 | I21: =I182 -> -64.9889 | J21: =J182 -> -36.3528 | ... AG21: =AG182 -> 0 | AH21: =SUM(C21:AG21) -> -59.46 | AU21: =U300 -> 569.66954
A22: 综合厂 用电量 （万千万时) | C22: =C183 -> 20.8993 | D22: =D183 -> 24.7176 | E22: =E183 -> 29.4552 | F22: =F183 -> 39.744 | G22: =G183 -> 39 | H22: =H183 -> 34.368 | I22: =I183 -> 34.3746 | J22: =J183 -> 33.9504 | ... AG22: =AG183 -> 0 | AH22: =SUM(C22:AG22) -> 1132.2085
C23: =C184 -> 19.8122 | D23: =D184 -> 19.26 | E23: =E184 -> 24.091752 | F23: =F184 -> 27.217848 | G23: =G184 -> 31.751544 | H23: =H184 -> 37.31016 | I23: =I184 -> 31.43438 | J23: =J184 -> 33.1032 | ... AG23: =AG184 -> 0 | AH23: =SUM(C23:AG23) -> 1140.6107
B24: 计划值 | C24: =C185 -> 12.800165 | D24: =D185 -> 16.403451 | E24: =E185 -> 22.095624 | F24: =F185 -> 34.306005 | G24: =G185 -> 32.336095 | H24: =H185 -> 33.410283 | I24: =I185 -> 28.042746 | J24: =J185 -> 17.260081 | ... AG24: =AG185 -> 0 | AH24: =SUM(C24:AG24) -> 1188.0273
B25: 与计划差值 | C25: =C186 -> 7.0120352 | D25: =D186 -> 2.8565489 | E25: =E186 -> 1.9961283 | F25: =F186 -> -7.0881573 | G25: =G186 -> -0.58455142 | H25: =H186 -> 3.8998773 | I25: =I186 -> 3.3916342 | J25: =J186 -> 15.843119 | ... AG25: =AG186 -> 0 | AH25: =SUM(C25:AG25) -> -47.416612
B26: 同比差值 | C26: =C187 -> -1.0871 | D26: =D187 -> -5.4576 | E26: =E187 -> -5.363448 | F26: =F187 -> -12.526152 | G26: =G187 -> -7.248456 | H26: =H187 -> 2.94216 | I26: =I187 -> -2.94022 | J26: =J187 -> -0.8472 | ... AG26: =AG187 -> 0 | AH26: =SUM(C26:AG26) -> 8.402184
A27: 综合 厂用电率 （%） | C27: =C188 -> 1.6492503 | D27: =D188 -> 0.39550691 | E27: =E188 -> 0.38305243 | F27: =F188 -> 0.3254717 | G27: =G188 -> 0.33015035 | H27: =H188 -> 0.29845769 | I27: =I188 -> 0.2932586 | J27: =J188 -> 0.29631336 | ... AF27: =AF188 -> 0.3157969 | AH27: =AH22/AH12 -> 0.32997056
C28: =C189 -> 9.8274802 | D28: =D189 -> 0.94190141 | E28: =E189 -> 0.48447056 | F28: =F189 -> 0.5756736 | G28: =G189 -> 0.67567978 | H28: =H189 -> 0.69401339 | I28: =I189 -> 0.64968543 | J28: =J189 -> 0.42782258 | ... AG28: =AG189 -> #DIV/0! | AH28: =AH23/AH13 -> 0.34152147
B29: 计划值 | C29: =C190 -> 0.27136 | D29: =D190 -> 1.27136 | E29: =E190 -> 2.27136 | F29: =F190 -> 0.27136 | G29: =G190 -> 0.27136 | H29: =H190 -> 0.27136 | I29: =I190 -> 0.27136 | J29: =J190 -> 0.27136 | ... AH29: =AH190 -> 0.27136
B30: 与计划差值 | C30: =C191 -> 9.5561202 | D30: =D191 -> -0.32945859 | E30: =E191 -> -1.7868894 | F30: =F191 -> 0.3043136 | G30: =G191 -> 0.40431978 | H30: =H191 -> 0.42265339 | I30: =I191 -> 0.37832543 | J30: =J191 -> 0.15646258 | ... AG30: =AG191 -> #DIV/0! | AH30: =SUM(C30:AG30) -> #DIV/0!
B31: 同比差值 | C31: =C192 -> 8.1782298 | D31: =D192 -> 0.5463945 | E31: =E192 -> 0.10141813 | F31: =F192 -> 0.25020191 | G31: =G192 -> 0.34552943 | H31: =H192 -> 0.3955557 | I31: =I192 -> 0.35642683 | J31: =J192 -> 0.13150922 | ... AG31: =AG192 -> #DIV/0! | AH31: =SUM(C31:AG31) -> #DIV/0!
A32: 外供汽量 (吨） | C32: =C193+C432 -> 0 | D32: =D193+D432 -> 0 | E32: =E193+E432 -> 0 | F32: =F193+F432 -> 0 | G32: =G193+G432 -> 0 | H32: =H193+H432 -> 0 | I32: =I193+I432 -> 0 | J32: =J193+J432 -> 0 | ... AG32: =AG193+AG432 -> 0 | AH32: =SUM(C32:AG32) -> 9741
C33: =C194 -> 0 | D33: =D194 -> 0 | E33: =E194 -> 0 | F33: =F194 -> 0 | G33: =G194 -> 0 | H33: =H194 -> 0 | I33: =I194 -> 0 | J33: =J194 -> 0 | ... AG33: =AG194 -> 0 | AH33: =SUM(C33:AG33) -> 10162.8
B34: 计划值 | C34: =C195 -> 0 | D34: =D195 -> 0 | E34: =E195 -> 0 | F34: =F195 -> 0 | G34: =G195 -> 0 | H34: =H195 -> 0 | I34: =I195 -> 0 | J34: =J195 -> 0 | ... AG34: =AG195 -> 0 | AH34: =SUM(C34:AG34) -> 9741
B35: 与计划差值 | C35: =C33-C34 -> 0 | D35: =D33-D34 -> 0 | E35: =E33-E34 -> 0 | F35: =F33-F34 -> 0 | G35: =G33-G34 -> 0 | H35: =H33-H34 -> 0 | I35: =I33-I34 -> 0 | J35: =J33-J34 -> 0 | ... AG35: =AG33-AG34 -> 0 | AH35: =SUM(C35:AG35) -> 421.8
B36: 同比差值 | C36: =C33-C32 -> 0 | D36: =D33-D32 -> 0 | E36: =E33-E32 -> 0 | F36: =F33-F32 -> 0 | G36: =G33-G32 -> 0 | H36: =H33-H32 -> 0 | I36: =I33-I32 -> 0 | J36: =J33-J32 -> 0 | ... AG36: =AG33-AG32 -> 0 | AH36: =SUM(C36:AG36) -> 421.8
A37: 供首站汽量 （吨） | C37: =C459+C475 -> 950 | D37: =D459+D475 -> 1712 | E37: =E459+E475 -> 2227 | F37: =F459+F475 -> 4469 | G37: =G459+G475 -> 4824 | H37: =H459+H475 -> 4437 | I37: =I459+I475 -> 5382 | J37: =J459+J475 -> 5314 | ... AG37: =AG459+AG475 -> 0 | AH37: =SUM(C37:AG37) -> 138239
C40: =C460+C476 -> 826 | D40: =D460+D476 -> 3008 | E40: =E460+E476 -> 3068 | F40: =F460+F476 -> 2806 | G40: =G460+G476 -> 3000 | H40: =H460+H476 -> 4897 | I40: =I460+I476 -> 2914 | J40: =J460+J476 -> 1149 | ... AG40: =AG460+AG476 -> 0 | AH40: =SUM(C40:AG40) -> 137945
B41: 同比差值 | C41: =C40-C37 -> -124 | D41: =D40-D37 -> 1296 | E41: =E40-E37 -> 841 | F41: =F40-F37 -> -1663 | G41: =G40-G37 -> -1824 | H41: =H40-H37 -> 460 | I41: =I40-I37 -> -2468 | J41: =J40-J37 -> -4165 | ... AG41: =AG40-AG37 -> 0 | AH41: =SUM(C41:AG41) -> -294
A42: 天然气炉 供汽量 （吨） | C42: =C432 -> 0 | D42: =D432 -> 0 | E42: =E432 -> 0 | F42: =F432 -> 0 | G42: =G432 -> 0 | H42: =H432 -> 0 | I42: =I432 -> 0 | J42: =J432 -> 0 | ... AG42: =AG432 -> 0 | AH42: =SUM(C42:AG42) -> 0
C43: =C433 -> 0 | D43: =D433 -> 0 | E43: =E433 -> 0 | F43: =F433 -> 0 | G43: =G433 -> 0 | H43: =H433 -> 0 | I43: =I433 -> 0 | J43: =J433 -> 0 | ... AG43: =AG433 -> 0 | AH43: =SUM(C43:AG43) -> 0
B44: 同比差值 | C44: =C43-C42 -> 0 | D44: =D43-D42 -> 0 | E44: =E43-E42 -> 0 | F44: =F43-F42 -> 0 | G44: =G43-G42 -> 0 | H44: =H43-H42 -> 0 | I44: =I43-I42 -> 0 | J44: =J43-J42 -> 0 | ... AG44: =AG43-AG42 -> 0 | AH44: =SUM(C44:AG44) -> 0
A45: 外供热总量 （吉焦） | C45: =C33*2.951694+C500+C501+C498 -> 19 | AH45: =SUM(C45:AG45) -> 19
C46: =C33*2.951694+C346+C469+C498+C485 -> 9401.6 | D46: =D33*2.951694+D346+D469+D498+D485 -> 15792.8 | E46: =E33*2.951694+E346+E469+E498+E485 -> 16392.8 | F46: =F33*2.951694+F346+F469+F498+F485 -> 16747.6 | G46: =G33*2.951694+G346+G469+G498+G485 -> 21495.6 | H46: =H33*2.951694+H346+H469+H498+H485 -> 22033.4 | I46: =I33*2.951694+I346+I469+I498+I485 -> 20153.4 | J46: =J33*2.951694+J346+J469+J498+J485 -> 17718.2 | ... AH46: =AH33*2.951694+AH346+AH469+AH498+AH485 -> 658438.48
B47: 计划值 | C47: =C200+C347+C436 -> 7531 | D47: =D200+D347+D436 -> 9651 | E47: =E200+E347+E436 -> 13000 | F47: =F200+F347+F436 -> 20183.779 | G47: =G200+G347+G436 -> 19025.451 | H47: =H200+H347+H436 -> 19657.117 | I47: =I200+I347+I436 -> 16498.788 | J47: =J200+J347+J436 -> 10155.468 | ... AG47: =AG200+AG347+AG436 -> 0 | AH47: =SUM(C47:AG47) -> 727062.1
B48: 与计划差值 | C48: =C46-C47 -> 1870.6 | D48: =D46-D47 -> 6141.8 | E48: =E46-E47 -> 3392.8 | F48: =F46-F47 -> -3436.1794 | G48: =G46-G47 -> 2470.1491 | H48: =H46-H47 -> 2376.2834 | I48: =I46-I47 -> 3654.6119 | J48: =J46-J47 -> 7562.7317 | ... AG48: =AG46-AG47 -> 0 | AH48: =SUM(C48:AG48) -> -68623.625
B49: 同比差值 | C49: =C46-C45 -> 9382.6 | D49: =D46-D45 -> 15792.8 | E49: =E46-E45 -> 16392.8 | F49: =F46-F45 -> 16747.6 | G49: =G46-G45 -> 21495.6 | H49: =H46-H45 -> 22033.4 | I49: =I46-I45 -> 20153.4 | J49: =J46-J45 -> 17718.2 | ... AG49: =AG46-AG45 -> 0 | AH49: =SUM(C49:AG49) -> 658419.48
A50: 电厂耗原煤量 （吨） | C50: =C203 -> 732 | D50: =D203 -> 599 | E50: =E203 -> 1177 | F50: =F203 -> 1281 | G50: =G203 -> 1217 | H50: =H203 -> 1148 | I50: =I203 -> 1170 | J50: =J203 -> 1237 | ... AG50: =AG203 -> 0 | AH50: =SUM(C50:AG50) -> 37380
C51: =C204 -> 292 | D51: =D204 -> 531 | E51: =E204 -> 585 | F51: =F204 -> 632 | G51: =G204 -> 716 | H51: =H204 -> 908 | I51: =I204 -> 609 | J51: =J204 -> 679 | ... AG51: =AG204 -> 0 | AH51: =SUM(C51:AG51) -> 34169
B52: 计划值 | C52: =C205 -> 464.67412 | D52: =D205 -> 595.48134 | E52: =E205 -> 802.11972 | F52: =F205 -> 1245.3834 | G52: =G205 -> 1173.8714 | H52: =H205 -> 1212.8667 | I52: =I205 -> 1018.0133 | J52: =J205 -> 626.5789 | ... AG52: =AG205 -> 0 | AH52: =SUM(C52:AG52) -> 43128.003
B53: 与计划差值 | C53: =C206 -> -172.67412 | D53: =D206 -> -64.481339 | E53: =E206 -> -217.11972 | F53: =F206 -> -613.38342 | G53: =G206 -> -457.87136 | H53: =H206 -> -304.86672 | I53: =I206 -> -409.01333 | J53: =J206 -> 52.421096 | ... AG53: =AG206 -> 0 | AH53: =SUM(C53:AG53) -> -8959.0028
B54: 同比差值 | C54: =C207 -> -440 | D54: =D207 -> -68 | E54: =E207 -> -592 | F54: =F207 -> -649 | G54: =G207 -> -501 | H54: =H207 -> -240 | I54: =I207 -> -561 | J54: =J207 -> -558 | ... AG54: =AG207 -> 0 | AH54: =SUM(C54:AG54) -> -3211
A55: 水炉耗原煤量 （吨） | C55: =C350 -> 345 | D55: =D350 -> 335 | E55: =E350 -> 416 | F55: =F350 -> 505 | G55: =G350 -> 213 | H55: =H350 -> 0 | I55: =I350 -> 0 | J55: =J350 -> 0 | ... AG55: =AG350 -> 0 | AH55: =SUM(C55:AG55) -> 11212
C56: =C351 -> 358 | D56: =D351 -> 389 | E56: =E351 -> 428 | F56: =F351 -> 492 | G56: =G351 -> 700 | H56: =H351 -> 444 | I56: =I351 -> 627 | J56: =J351 -> 619 | ... AG56: =AG351 -> 0 | AH56: =SUM(C56:AG56) -> 9019
B57: 计划值 | C57: =C352 -> 0 | D57: =D352 -> 0 | E57: =E352 -> 0 | F57: =F352 -> -0.013002542 | G57: =G352 -> 0.026571611 | H57: =H352 -> 0.006870182 | I57: =I352 -> -0.012488657 | J57: =J352 -> 0.027599381 | ... AG57: =AG352 -> 0 | AH57: =SUM(C57:AG57) -> 1655.0801
B58: 与计划差值 | C58: =C353 -> 358 | D58: =D353 -> 389 | E58: =E353 -> 428 | F58: =F353 -> 492.013 | G58: =G353 -> 699.97343 | H58: =H353 -> 443.99313 | I58: =I353 -> 627.01249 | J58: =J353 -> 618.9724 | ... AG58: =AG353 -> 0 | AH58: =SUM(C58:AG58) -> 7363.9199
B59: 同比差值 | C59: =C354 -> 13 | D59: =D354 -> 54 | E59: =E354 -> 12 | F59: =F354 -> -13 | G59: =G354 -> 487 | H59: =H354 -> 444 | I59: =I354 -> 627 | J59: =J354 -> 619 | ... AG59: =AG354 -> 0 | AH59: =SUM(C59:AG59) -> -2193
A60: 电厂耗标煤量 （吨） | C60: =C208 -> 523.49939 | D60: =D208 -> 414.48478 | E60: =E208 -> 824.4783 | F60: =F208 -> 903.88563 | G60: =G208 -> 848.76075 | H60: =H208 -> 788.10427 | I60: =I208 -> 803.20732 | J60: =J208 -> 893.09813 | ... AG60: =AG208 -> 0 | AH60: =SUM(C60:AG60) -> 26081.758
C61: =C209 -> 213.8092 | D61: =D209 -> 387.36113 | E61: =E209 -> 432.1431 | F61: =F209 -> 468.58742 | G61: =G209 -> 507.17074 | H61: =H209 -> 646.57977 | I61: =I209 -> 455.48246 | J61: =J209 -> 496.02122 | ... AG61: =AG209 -> 0 | AH61: =SUM(C61:AG61) -> 24795.181
B62: 计划值 | C62: =C210 -> 363.87053 | D62: =D210 -> 466.30122 | E62: =E210 -> 628.11273 | F62: =F210 -> 975.21748 | G62: =G210 -> 919.21882 | H62: =H210 -> 949.75476 | I62: =I210 -> 797.17168 | J62: =J210 -> 490.65267 | ... AG62: =AG210 -> 0 | AH62: =SUM(C62:AG62) -> 33772.075
B63: 与计划差值 | C63: =C211 -> -150.06133 | D63: =D211 -> -78.940094 | E63: =E211 -> -195.96962 | F63: =F211 -> -506.63006 | G63: =G211 -> -412.04808 | H63: =H211 -> -303.17498 | I63: =I211 -> -341.68922 | J63: =J211 -> 5.3685514 | ... AG63: =AG211 -> 0 | AH63: =SUM(C63:AG63) -> -8976.894
B64: 同比差值 | C64: =C212 -> -309.69019 | D64: =D212 -> -27.123652 | E64: =E212 -> -392.3352 | F64: =F212 -> -435.29821 | G64: =G212 -> -341.59001 | H64: =H212 -> -141.5245 | I64: =I212 -> -347.72485 | J64: =J212 -> -397.07691 | ... AG64: =AG212 -> 0 | AH64: =SUM(C64:AG64) -> -1286.5764
A65: 水炉耗标煤量 （吨） | C65: =C355 -> 209.76866 | D65: =D355 -> 211.68964 | E65: =E355 -> 261.73877 | F65: =F355 -> 328.59117 | G65: =G355 -> 132.05302 | H65: =H355 -> 0 | I65: =I355 -> 0 | J65: =J355 -> 0 | ... AG65: =AG355 -> 0 | AH65: =SUM(C65:AG65) -> 7223.4356
C66: =C356 -> 273.98458 | D66: =D356 -> 287.09124 | E66: =E356 -> 315.14399 | F66: =F356 -> 348.33493 | G66: =G356 -> 514.70588 | H66: =H356 -> 317.9869 | I66: =I356 -> 454.1835 | J66: =J356 -> 443.95319 | ... AG66: =AG356 -> 0 | AH66: =SUM(C66:AG66) -> 6534.0781
B67: 计划值 | C67: =C357 -> 0 | D67: =D357 -> 0 | E67: =E357 -> 0 | F67: =F357 -> -0.0083459745 | G67: =G357 -> 0.017055587 | H67: =H357 -> 0.0044097811 | I67: =I357 -> -0.0080161259 | J67: =J357 -> 0.017715284 | ... AG67: =AG357 -> 0 | AH67: =SUM(C67:AG67) -> 1062.3505
B68: 与计划差值 | C68: =C358 -> 273.98458 | D68: =D358 -> 287.09124 | E68: =E358 -> 315.14399 | F68: =F358 -> 348.34327 | G68: =G358 -> 514.68883 | H68: =H358 -> 317.98249 | I68: =I358 -> 454.19152 | J68: =J358 -> 443.93547 | ... AG68: =AG358 -> 0 | AH68: =SUM(C68:AG68) -> 5471.7276
B69: 同比差值 | C69: =C359 -> 64.215914 | D69: =D359 -> 75.401597 | E69: =E359 -> 53.405214 | F69: =F359 -> 19.743756 | G69: =G359 -> 382.65286 | H69: =H359 -> 317.9869 | I69: =I359 -> 454.1835 | J69: =J359 -> 443.95319 | ... AG69: =AG359 -> 0 | AH69: =SUM(C69:AG69) -> -689.35751
A70: 耗天然气量 （立方米） | C70: =C444 -> 0 | D70: =D444 -> 0 | E70: =E444 -> 0 | F70: =F444 -> 0 | G70: =G444 -> 0 | H70: =H444 -> 0 | I70: =I444 -> 0 | J70: =J444 -> 0 | ... AG70: =AG444 -> 0 | AH70: =SUM(C70:AG70) -> 0
C71: =C445 -> 0 | D71: =D445 -> 0 | E71: =E445 -> 0 | F71: =F445 -> 0 | G71: =G445 -> 0 | H71: =H445 -> 0 | I71: =I445 -> 0 | J71: =J445 -> 0 | ... AG71: =AG445 -> 0 | AH71: =SUM(C71:AG71) -> 0
B72: 计划值 | C72: =C445 -> 0 | D72: =D445 -> 0 | E72: =E445 -> 0 | F72: =F445 -> 0 | G72: =G445 -> 0 | H72: =H445 -> 0 | I72: =I445 -> 0 | J72: =J445 -> 0 | ... AG72: =AG445 -> 0 | AH72: =SUM(C72:AG72) -> 0
B73: 与计划差值 | C73: =C71-C72 -> 0 | D73: =D71-D72 -> 0 | E73: =E71-E72 -> 0 | F73: =F71-F72 -> 0 | G73: =G71-G72 -> 0 | H73: =H71-H72 -> 0 | I73: =I71-I72 -> 0 | J73: =J71-J72 -> 0 | ... AG73: =AG71-AG72 -> 0 | AH73: =SUM(C73:AG73) -> 0
B74: 同比差值 | C74: =C71-C70 -> 0 | D74: =D71-D70 -> 0 | E74: =E71-E70 -> 0 | F74: =F71-F70 -> 0 | G74: =G71-G70 -> 0 | H74: =H71-H70 -> 0 | I74: =I71-I70 -> 0 | J74: =J71-J70 -> 0 | ... AG74: =AG71-AG70 -> 0 | AH74: =SUM(C74:AG74) -> 0
A75: 总自来水量 （吨） | C75: =C221 -> 3404 | D75: =D221 -> 5243 | E75: =E221 -> 4770 | F75: =F221 -> 4396 | G75: =G221 -> 4671 | H75: =H221 -> 5017 | I75: =I221 -> 5880 | J75: =J221 -> 1481 | ... AG75: =AG221 -> 0 | AH75: =SUM(C75:AG75) -> 137297
C76: =C219 -> 3542 | D76: =D219 -> 2524 | E76: =E219 -> 1058 | F76: =F219 -> 2039 | G76: =G219 -> 2087 | H76: =H219 -> 2802 | I76: =I219 -> 1948 | J76: =J219 -> 2326 | ... AG76: =AG219 -> 0 | AH76: =SUM(C76:AG76) -> 55790
B77: 同比差值 | C77: =C76-C75 -> 138 | D77: =D76-D75 -> -2719 | E77: =E76-E75 -> -3712 | F77: =F76-F75 -> -2357 | G77: =G76-G75 -> -2584 | H77: =H76-H75 -> -2215 | I77: =I76-I75 -> -3932 | J77: =J76-J75 -> 845 | ... AG77: =AG76-AG75 -> 0 | AH77: =SUM(C77:AG77) -> -81507
A78: 再生水量 （吨） | C78: =C226+C365 -> 2987 | D78: =D226+D365 -> 3716 | E78: =E226+E365 -> 3432 | F78: =F226+F365 -> 3117 | G78: =G226+G365 -> 2885 | H78: =H226+H365 -> 3169 | I78: =I226+I365 -> 3197 | J78: =J226+J365 -> 1661 | ... AG78: =AG226+AG365 -> 0 | AH78: =SUM(C78:AG78) -> 93818
C79: =C227 -> 3431 | D79: =D227 -> 3267 | E79: =E227 -> 2743 | F79: =F227 -> 2546 | G79: =G227 -> 3091 | H79: =H227 -> 3443 | I79: =I227 -> 2498 | J79: =J227 -> 3319 | ... AG79: =AG227 -> 0 | AH79: =SUM(C79:AG79) -> 94484
B80: 同比差值 | C80: =C79-C78 -> 444 | D80: =D79-D78 -> -449 | E80: =E79-E78 -> -689 | F80: =F79-F78 -> -571 | G80: =G79-G78 -> 206 | H80: =H79-H78 -> 274 | I80: =I79-I78 -> -699 | J80: =J79-J78 -> 1658 | ... AG80: =AG79-AG78 -> 0 | AH80: =SUM(C80:AG80) -> 666
A81: 电厂耗水量 （吨） | C81: =C221 -> 3404 | D81: =D221 -> 5243 | E81: =E221 -> 4770 | F81: =F221 -> 4396 | G81: =G221 -> 4671 | H81: =H221 -> 5017 | I81: =I221 -> 5880 | J81: =J221 -> 1481 | ... AG81: =AG221 -> 0 | AH81: =SUM(C81:AG81) -> 137297
C82: =C222 -> 3233 | D82: =D222 -> 3882 | E82: =E222 -> 1806 | F82: =F222 -> 2623 | G82: =G222 -> 3059 | H82: =H222 -> 4297 | I82: =I222 -> 3004 | J82: =J222 -> 4308 | ... AG82: =AG222 -> 0 | AH82: =SUM(C82:AG82) -> 102306
B83: 计划值 | C83: =C223 -> 3552.5333 | D83: =D223 -> 3552.5333 | E83: =E223 -> 3552.5333 | F83: =F223 -> 3552.5333 | G83: =G223 -> 3552.5333 | H83: =H223 -> 3552.5333 | I83: =I223 -> 3552.5333 | J83: =J223 -> 3552.5333 | ... AG83: =AG223 -> 0 | AH83: =SUM(C83:AG83) -> 116317
B84: 与计划差值 | C84: =C224 -> -319.53333 | D84: =D224 -> 329.46667 | E84: =E224 -> -1746.5333 | F84: =F224 -> -929.53333 | G84: =G224 -> -493.53333 | H84: =H224 -> 744.46667 | I84: =I224 -> -548.53333 | J84: =J224 -> 755.46667 | ... AG84: =AG224 -> 0 | AH84: =SUM(C84:AG84) -> -14011
B85: 同比差值 | C85: =C225 -> -171 | D85: =D225 -> -1361 | E85: =E225 -> -2964 | F85: =F225 -> -1773 | G85: =G225 -> -1612 | H85: =H225 -> -720 | I85: =I225 -> -2876 | J85: =J225 -> 2827 | ... AG85: =AG225 -> 0 | AH85: =SUM(C85:AG85) -> -34991
A86: 耗柴油量 （吨） | C86: =C229+C373 -> 26.1 | D86: =D229+D373 -> 0 | E86: =E229+E373 -> 13.5 | F86: =F229+F373 -> 0 | G86: =G229+G373 -> 0 | H86: =H229+H373 -> 0 | I86: =I229+I373 -> 0 | J86: =J229+J373 -> 0 | ... AG86: =AG229+AG373 -> 0 | AH86: =SUM(C86:AG86) -> 74.7
C87: =C230+C373 -> 42.3 | D87: =D230+D374 -> 0 | E87: =E230+E374 -> 0.9 | F87: =F230+F374 -> 10.8 | G87: =G230+G374 -> 27.9 | H87: =H230+H374 -> 10.8 | I87: =I230+I374 -> 3.6 | J87: =J230+J374 -> 16.2 | K87: =K230+K374 -> 1.8 | ... AG87: =AG230+AG374 -> 0 | AH87: =SUM(C87:AG87) -> 196.2
B88: 计划值 | C88: =C231+C375 -> 29 | D88: =D231+D375 -> 0 | E88: =E231+E375 -> 11.5 | F88: =F231+F375 -> 0 | G88: =G231+G375 -> 0 | H88: =H231+H375 -> 0 | I88: =I231+I375 -> 4.5 | J88: =J231+J375 -> 0 | ... AG88: =AG231+AG375 -> 0 | AH88: =SUM(C88:AG88) -> 77
B89: 与计划差值 | C89: =C87-C88 -> 13.3 | D89: =D87-D88 -> 0 | E89: =E87-E88 -> -10.6 | F89: =F87-F88 -> 10.8 | G89: =G87-G88 -> 27.9 | H89: =H87-H88 -> 10.8 | I89: =I87-I88 -> -0.9 | J89: =J87-J88 -> 16.2 | ... AG89: =AG87-AG88 -> 0 | AH89: =SUM(C89:AG89) -> 119.2
B90: 同比差值 | C90: =C87-C86 -> 16.2 | D90: =D87-D86 -> 0 | E90: =E87-E86 -> -12.6 | F90: =F87-F86 -> 10.8 | G90: =G87-G86 -> 27.9 | H90: =H87-H86 -> 10.8 | I90: =I87-I86 -> 3.6 | J90: =J87-J86 -> 16.2 | ... AG90: =AG87-AG86 -> 0 | AH90: =SUM(C90:AG90) -> 121.5
A91: 外购电量 （千万时） | C91: =C234 -> 18.3649 | D91: =D234 -> 0 | E91: =E234 -> 0 | F91: =F234 -> 0 | G91: =G234 -> 0 | H91: =H234 -> 0 | I91: =I234 -> 0 | J91: =J234 -> 0 | ... AG91: =AG234 -> 0 | AH91: =SUM(C91:AG91) -> 18.3649
C92: =C235 -> 19.4333 | D92: =D235 -> 12.7694 | E92: =E235 -> 7.073352 | F92: =F235 -> 8.449848 | G92: =G235 -> 2.975544 | H92: =H235 -> 7.15176 | I92: =I235 -> 0.90288 | J92: =J235 -> 0 | ... AG92: =AG235 -> 0 | AH92: =SUM(C92:AG92) -> 58.756084
B93: 计划值 | C93: =C236 -> 0 | D93: =D236 -> 0 | E93: =E236 -> 0 | F93: =F236 -> 0 | G93: =G236 -> 0 | H93: =H236 -> 0 | I93: =I236 -> 0 | J93: =J236 -> 0 | ... AG93: =AG236 -> 0 | AH93: =SUM(C93:AG93) -> 0
B94: 与计划差值 | C94: =C237 -> 19.4333 | D94: =D237 -> 12.7694 | E94: =E237 -> 7.073352 | F94: =F237 -> 8.449848 | G94: =G237 -> 2.975544 | H94: =H237 -> 7.15176 | I94: =I237 -> 0.90288 | J94: =J237 -> 0 | ... AG94: =AG237 -> 0 | AH94: =SUM(C94:AG94) -> 58.756084
B95: 同比差值 | C95: =C238 -> 1.0684 | D95: =D238 -> 12.7694 | E95: =E238 -> 7.073352 | F95: =F238 -> 8.449848 | G95: =G238 -> 2.975544 | H95: =H238 -> 7.15176 | I95: =I238 -> 0.90288 | J95: =J238 -> 0 | ... AG95: =AG238 -> 0 | AH95: =SUM(C95:AG95) -> 40.391184
A96: 石灰石 (含水炉）（吨） | C96: =C241+C383 -> 13.74 | D96: =D241+D383 -> 54.8 | E96: =E241+E383 -> 60.4 | F96: =F241+F383 -> 65.8 | G96: =G241+G383 -> 54.2 | H96: =H241+H383 -> 48 | I96: =I241+I383 -> 44 | J96: =J241+J383 -> 51 | ... AG96: =AG241+AG383 -> 0 | AH96: =SUM(C96:AG96) -> 1225.22
C97: =C242+C384 -> 69.57 | D97: =D242+D384 -> 30.02 | E97: =E242+E384 -> 29.2 | F97: =F242+F384 -> 36.53 | G97: =G242+G384 -> 39.43 | H97: =H242+H384 -> 31.83 | I97: =I242+I384 -> 33 | J97: =J242+J384 -> 38.6 | ... AG97: =AG242+AG384 -> 0 | AH97: =SUM(C97:AG97) -> 1197.98
B98: 计划值 | C98: =C243+C385 -> 14.276002 | D98: =D243+D385 -> 18.294742 | E98: =E243+E385 -> 24.643212 | F98: =F243+F385 -> 38.261124 | G98: =G243+G385 -> 36.065019 | H98: =H243+H385 -> 37.262594 | I98: =I243+I385 -> 31.275733 | J98: =J243+J385 -> 19.25079 | ... AG98: =AG243+AG385 -> 0 | AH98: =SUM(C98:AG98) -> 1364.0006
B99: 与计划差值 | C99: =C97-C98 -> 55.293998 | D99: =D97-D98 -> 11.725258 | E99: =E97-E98 -> 4.5567878 | F99: =F97-F98 -> -1.731124 | G99: =G97-G98 -> 3.3649807 | H99: =H97-H98 -> -5.4325943 | I99: =I97-I98 -> 1.7242667 | J99: =J97-J98 -> 19.34921 | ... AG99: =AG97-AG98 -> 0 | AH99: =SUM(C99:AG99) -> -166.02062
B100: 同比差值 | C100: =C97-C96 -> 55.83 | D100: =D97-D96 -> -24.78 | E100: =E97-E96 -> -31.2 | F100: =F97-F96 -> -29.27 | G100: =G97-G96 -> -14.77 | H100: =H97-H96 -> -16.17 | I100: =I97-I96 -> -11 | J100: =J97-J96 -> -12.4 | ... AG100: =AG97-AG96 -> 0 | AH100: =SUM(C100:AG100) -> -27.24
A101: 氨水 (含水炉） （吨） | C101: =C246+C388 -> 3.82 | D101: =D246+D388 -> 8.3 | E101: =E246+E388 -> 10.9 | F101: =F246+F388 -> 8.98 | G101: =G246+G388 -> 7.8 | H101: =H246+H388 -> 7.2 | I101: =I246+I388 -> 8.1 | J101: =J246+J388 -> 9 | ... AG101: =AG246+AG388 -> 0 | AH101: =SUM(C101:AG101) -> 284.13
C102: =C247+C389 -> 1.73 | D102: =D247+D389 -> 3.55 | E102: =E247+E389 -> 4.1 | F102: =F247+F389 -> 4.06 | G102: =G247+G389 -> 5.63 | H102: =H247+H389 -> 5.87 | I102: =I247+I389 -> 4.5 | J102: =J247+J389 -> 4.45 | ... AG102: =AG247+AG389 -> 0 | AH102: =SUM(C102:AG102) -> 216.74
...
